Workbook

Sheet Financials
B2: Years

Sheet historicalFS
E1: h
B2: ="Historical financial Statement - "&'Data Sheet'!B1 -> Historical financial Statement - HONDA INDIA POWER PRODUCTS LTD
B3: Years | D3: ='Data Sheet'!B16 -> 42460 | E3: ='Data Sheet'!C16 -> 42825 | F3: ='Data Sheet'!D16 -> 43190 | G3: ='Data Sheet'!E16 -> 43555 | H3: ='Data Sheet'!F16 -> 43921 | I3: ='Data Sheet'!G16 -> 44286 | J3: ='Data Sheet'!H16 -> 44651 | K3: ='Data Sheet'!I16 -> 45016 | ... M3: ='Data Sheet'!K16 -> 45747 | N3: LTM
A5: # | B5: Income Statement
B6: Sales | D6: =IFERROR('Data Sheet'!B17,0) -> 672.81 | E6: =IFERROR('Data Sheet'!C17,0) -> 701.78 | F6: =IFERROR('Data Sheet'!D17,0) -> 767.8 | G6: =IFERROR('Data Sheet'!E17,0) -> 815.88 | H6: =IFERROR('Data Sheet'!F17,0) -> 848.64 | I6: =IFERROR('Data Sheet'!G17,0) -> 938.94 | J6: =IFERROR('Data Sheet'!H17,0) -> 1156.29 | K6: =IFERROR('Data Sheet'!I17,0) -> 1246.29 | L6: =IFERROR('Data Sheet'!J17,0) -> 989.07 | M6: ='Data Sheet'!K17 -> 794.23 | N6: =IFERROR(SUM('[1]Data Sheet'!$H$42:$K$42),0) -> 803.38
B7: Sales Growth | D7: - | E7: =IFERROR(E6/D6-1,0) -> 0.043058219 | F7: =IFERROR(F6/E6-1,0) -> 0.094075066 | G7: =IFERROR(G6/F6-1,0) -> 0.062620474 | H7: =IFERROR(H6/G6-1,0) -> 0.040152964 | I7: =IFERROR(I6/H6-1,0) -> 0.10640554 | J7: =IFERROR(J6/I6-1,0) -> 0.23148444 | K7: =IFERROR(K6/J6-1,0) -> 0.077835145 | L7: =IFERROR(L6/K6-1,0) -> -0.20638856 | ... N7: =IFERROR(N6/M6-1,0) -> 0.011520592
B9: COGS | D9: =IFERROR(SUM('Data Sheet'!B18,'Data Sheet'!B20:B21)-1*'Data Sheet'!B19,0) -> 409.43 | E9: =IFERROR(SUM('Data Sheet'!C18,'Data Sheet'!C20:C21)-1*'Data Sheet'!C19,0) -> 431.5 | F9: =IFERROR(SUM('Data Sheet'!D18,'Data Sheet'!D20:D21)-1*'Data Sheet'!D19,0) -> 471.77 | G9: =IFERROR(SUM('Data Sheet'!E18,'Data Sheet'!E20:E21)-1*'Data Sheet'!E19,0) -> 519.32 | H9: =IFERROR(SUM('Data Sheet'!F18,'Data Sheet'!F20:F21)-1*'Data Sheet'!F19,0) -> 524.38 | I9: =IFERROR(SUM('Data Sheet'!G18,'Data Sheet'!G20:G21)-1*'Data Sheet'!G19,0) -> 626.31 | J9: =IFERROR(SUM('Data Sheet'!H18,'Data Sheet'!H20:H21)-1*'Data Sheet'!H19,0) -> 753.97 | K9: =IFERROR(SUM('Data Sheet'!I18,'Data Sheet'!I20:I21)-1*'Data Sheet'!I19,0) -> 778.85 | ... N9: =IFERROR(SUM('Data Sheet'!L18,'Data Sheet'!L20:L21)-1*'Data Sheet'!L19,0) -> 0
B10: cogs% sales | D10: =D9/D6 -> 0.60853733 | E10: =E9/E6 -> 0.61486506 | F10: =F9/F6 -> 0.61444387 | G10: =G9/G6 -> 0.63651517 | H10: =H9/H6 -> 0.6179063 | I10: =I9/I6 -> 0.66703943 | J10: =J9/J6 -> 0.6520596 | K10: =K9/K6 -> 0.62493481 | ... N10: =N9/N6 -> 0
B12: Gross profit | D12: =D6-D9 -> 263.38 | E12: =E6-E9 -> 270.28 | F12: =F6-F9 -> 296.03 | G12: =G6-G9 -> 296.56 | H12: =H6-H9 -> 324.26 | I12: =I6-I9 -> 312.63 | J12: =J6-J9 -> 402.32 | K12: =K6-K9 -> 467.44 | ... N12: =N6-N9 -> 803.38
B13: gross margin | D13: =IFERROR(D12/D6,0) -> 0.39146267 | E13: =IFERROR(E12/E6,0) -> 0.38513494 | F13: =IFERROR(F12/F6,0) -> 0.38555613 | G13: =IFERROR(G12/G6,0) -> 0.36348483 | H13: =IFERROR(H12/H6,0) -> 0.3820937 | I13: =IFERROR(I12/I6,0) -> 0.33296057 | J13: =IFERROR(J12/J6,0) -> 0.3479404 | K13: =IFERROR(K12/K6,0) -> 0.37506519 | ... N13: =IFERROR(N12/N6,0) -> 1
B15: S&G Expenses | D15: =IFERROR(SUM('Data Sheet'!B23:B25),0) -> 120.61 | E15: =IFERROR(SUM('Data Sheet'!C23:C25),0) -> 117.75 | F15: =IFERROR(SUM('Data Sheet'!D23:D25),0) -> 121.9 | G15: =IFERROR(SUM('Data Sheet'!E23:E25),0) -> 121.41 | H15: =IFERROR(SUM('Data Sheet'!F23:F25),0) -> 136.94 | I15: =IFERROR(SUM('Data Sheet'!G23:G25),0) -> 147.22 | J15: =IFERROR(SUM('Data Sheet'!H23:H25),0) -> 199.09 | K15: =IFERROR(SUM('Data Sheet'!I23:I25),0) -> 206.89 | ... N15: =IFERROR(SUM('Data Sheet'!L23:L25),0) -> 0
B16: S&G Expenses% sales | D16: =D15/D6 -> 0.17926309 | E16: =E15/E6 -> 0.16778763 | F16: =F15/F6 -> 0.1587653 | G16: =G15/G6 -> 0.14880865 | H16: =H15/H6 -> 0.16136406 | I16: =I15/I6 -> 0.15679383 | J16: =J15/J6 -> 0.17217999 | K16: =K15/K6 -> 0.1660047 | ... N16: =N15/N6 -> 0
B18: EBITDA | D18: =D12-D15 -> 142.77 | E18: =E12-E15 -> 152.53 | F18: =F12-F15 -> 174.13 | G18: =G12-G15 -> 175.15 | H18: =H12-H15 -> 187.32 | I18: =I12-I15 -> 165.41 | J18: =J12-J15 -> 203.23 | K18: =K12-K15 -> 260.55 | ... M18: =M12-M15 -> 179.12
B19: EBITDA margin | D19: =IFERROR(D18/D6,0) -> 0.21219958 | E19: =IFERROR(E18/E6,0) -> 0.21734732 | F19: =IFERROR(F18/F6,0) -> 0.22679083 | G19: =IFERROR(G18/G6,0) -> 0.21467618 | H19: =IFERROR(H18/H6,0) -> 0.22072964 | I19: =IFERROR(I18/I6,0) -> 0.17616674 | J19: =IFERROR(J18/J6,0) -> 0.17576041 | K19: =IFERROR(K18/K6,0) -> 0.20906049 | ... N19: =IFERROR(N18/N6,0) -> 0
B21: Interest | D21: =IFERROR('Data Sheet'!B27,0) -> 0.9 | E21: =IFERROR('Data Sheet'!C27,0) -> 0.87 | F21: =IFERROR('Data Sheet'!D27,0) -> 0.67 | G21: =IFERROR('Data Sheet'!E27,0) -> 0.57 | H21: =IFERROR('Data Sheet'!F27,0) -> 0.71 | I21: =IFERROR('Data Sheet'!G27,0) -> 0.67 | J21: =IFERROR('Data Sheet'!H27,0) -> 0.93 | K21: =IFERROR('Data Sheet'!I27,0) -> 0.65 | ... M21: =IFERROR('Data Sheet'!K27,0) -> 0.52 | N21: =IFERROR(SUM('Data Sheet'!H46:K46),0) -> 0.44 | T21: =(D18-D24)/D21 -> 132.16667
B22: Interest margin | D22: =D21/D6 -> 0.0013376733 | E22: =E21/E6 -> 0.0012397048 | F22: =F21/F6 -> 0.00087262308 | G22: =G21/G6 -> 0.00069863215 | H22: =H21/H6 -> 0.00083663273 | I22: =I21/I6 -> 0.00071357062 | J22: =J21/J6 -> 0.0008042965 | K22: =K21/K6 -> 0.00052154795 | ... N22: =N21/N6 -> 0.00054768603
B24: Depriciation | D24: =IFERROR('Data Sheet'!B26,0) -> 23.82 | E24: =IFERROR('Data Sheet'!C26,0) -> 23.45 | F24: =IFERROR('Data Sheet'!D26,0) -> 22.51 | G24: =IFERROR('Data Sheet'!E26,0) -> 21.13 | H24: =IFERROR('Data Sheet'!F26,0) -> 22.08 | I24: =IFERROR('Data Sheet'!G26,0) -> 20.26 | J24: =IFERROR('Data Sheet'!H26,0) -> 18.52 | K24: =IFERROR('Data Sheet'!I26,0) -> 20.78 | ... M24: =IFERROR('Data Sheet'!K26,0) -> 21.8 | N24: =IFERROR(SUM('Data Sheet'!H45:K45),0) -> 22.34
B25: Depriciation % sales | D25: =D24/D6 -> 0.035403754 | E25: =E24/E6 -> 0.03341503 | F25: =F24/F6 -> 0.029317531 | G25: =G24/G6 -> 0.025898416 | H25: =H24/H6 -> 0.0260181 | I25: =I24/I6 -> 0.021577524 | J25: =J24/J6 -> 0.016016743 | K25: =K24/K6 -> 0.016673487 | ... N25: =N24/N6 -> 0.027807513
B27: EBT | D27: =IFERROR(D18-SUM(D21,D24),0) -> 118.05 | E27: =IFERROR(E18-SUM(E21,E24),0) -> 128.21 | F27: =IFERROR(F18-SUM(F21,F24),0) -> 150.95 | G27: =IFERROR(G18-SUM(G21,G24),0) -> 153.45 | H27: =IFERROR(H18-SUM(H21,H24),0) -> 164.53 | I27: =IFERROR(I18-SUM(I21,I24),0) -> 144.48 | J27: =IFERROR(J18-SUM(J21,J24),0) -> 183.78 | K27: =IFERROR(K18-SUM(K21,K24),0) -> 239.12 | ... N27: =IFERROR(N18-SUM(N21,N24),0) -> -22.78
B28: EBT%sales | D28: =D27/D6 -> 0.17545815 | E28: =E27/E6 -> 0.18269258 | F28: =F27/F6 -> 0.19660068 | G28: =G27/G6 -> 0.18807913 | H28: =H27/H6 -> 0.19387491 | I28: =I27/I6 -> 0.15387565 | J28: =J27/J6 -> 0.15893937 | K28: =K27/K6 -> 0.19186546 | ... N28: =N27/N6 -> -0.028355199
B30: Tax | D30: =IFERROR('Data Sheet'!B29,0) -> 26.24 | E30: =IFERROR('Data Sheet'!C29,0) -> 30.33 | F30: =IFERROR('Data Sheet'!D29,0) -> 32.93 | G30: =IFERROR('Data Sheet'!E29,0) -> 29.16 | H30: =IFERROR('Data Sheet'!F29,0) -> 23.91 | I30: =IFERROR('Data Sheet'!G29,0) -> 17.47 | J30: =IFERROR('Data Sheet'!H29,0) -> 25.53 | K30: =IFERROR('Data Sheet'!I29,0) -> 30.31 | ... M30: =IFERROR('Data Sheet'!K29,0) -> 27.76 | N30: =IFERROR(SUM('Data Sheet'!H48:K48),0) -> 26.35
B31: effective tax rate | D31: =D30/D27 -> 0.2222787 | E31: =E30/E27 -> 0.23656501 | F31: =F30/F27 -> 0.21815171 | G31: =G30/G27 -> 0.19002933 | H31: =H30/H27 -> 0.14532304 | I31: =I30/I27 -> 0.12091639 | J31: =J30/J27 -> 0.1389161 | K31: =K30/K27 -> 0.12675644 | ... N31: =N30/N27 -> -1.1567164
B33: Net Profit | D33: =D27-D30 -> 91.81 | E33: =E27-E30 -> 97.88 | F33: =F27-F30 -> 118.02 | G33: =G27-G30 -> 124.29 | H33: =H27-H30 -> 140.62 | I33: =I27-I30 -> 127.01 | J33: =J27-J30 -> 158.25 | K33: =K27-K30 -> 208.81 | ... N33: =N27-N30 -> -49.13
B34: net margin | D34: =D33/D6 -> 0.13645754 | E34: =E33/E6 -> 0.13947391 | F34: =F33/F6 -> 0.1537119 | G34: =G33/G6 -> 0.15233858 | H34: =H33/H6 -> 0.16570041 | I34: =I33/I6 -> 0.13526956 | J34: =J33/J6 -> 0.13686013 | K34: =K33/K6 -> 0.16754527 | ... N34: =N33/N6 -> -0.061154124
B36: no. of equity shares | D36: =IFERROR('Data Sheet'!B93,0) -> 1.01 | E36: =IFERROR('Data Sheet'!C93,0) -> 1.01 | F36: =IFERROR('Data Sheet'!D93,0) -> 1.01 | G36: =IFERROR('Data Sheet'!E93,0) -> 1.01 | H36: =IFERROR('Data Sheet'!F93,0) -> 1.01 | I36: =IFERROR('Data Sheet'!G93,0) -> 1.01 | J36: =IFERROR('Data Sheet'!H93,0) -> 1.01 | K36: =IFERROR('Data Sheet'!I93,0) -> 1.01 | ... N36: =IFERROR('Data Sheet'!L93,0) -> 0
B38: EPS | D38: =IFERROR(D33/D36,0) -> 90.90099 | E38: =IFERROR(E33/E36,0) -> 96.910891 | F38: =IFERROR(F33/F36,0) -> 116.85149 | G38: =IFERROR(G33/G36,0) -> 123.05941 | H38: =IFERROR(H33/H36,0) -> 139.22772 | I38: =IFERROR(I33/I36,0) -> 125.75248 | J38: =IFERROR(J33/J36,0) -> 156.68317 | K38: =IFERROR(K33/K36,0) -> 206.74257 | ... N38: =IFERROR(N33/N36,0) -> 0
B39: EPS growth% | E39: =IFERROR(E38/D38-1,0) -> 0.066114802 | F39: =IFERROR(F38/E38-1,0) -> 0.20576216 | G39: =IFERROR(G38/F38-1,0) -> 0.053126589 | H39: =IFERROR(H38/G38-1,0) -> 0.13138627 | I39: =IFERROR(I38/H38-1,0) -> -0.096785663 | J39: =IFERROR(J38/I38-1,0) -> 0.24596488 | K39: =IFERROR(K38/J38-1,0) -> 0.31949447 | L39: =IFERROR(L38/K38-1,0) -> -0.37890906 | ... N39: =IFERROR(N38/M38-1,0) -> -1
B41: Dividend per share | D41: =IFERROR('Data Sheet'!B31/D36,0) -> 6.019802 | E41: =IFERROR('Data Sheet'!C31/E36,0) -> 7.5247525 | F41: =IFERROR('Data Sheet'!D31/F36,0) -> 9.039604 | G41: =IFERROR('Data Sheet'!E31/G36,0) -> 10.039604 | H41: =IFERROR('Data Sheet'!F31/H36,0) -> 12.554455 | I41: =IFERROR('Data Sheet'!G31/I36,0) -> 10.039604 | J41: =IFERROR('Data Sheet'!H31/J36,0) -> 15.059406 | K41: =IFERROR('Data Sheet'!I31/K36,0) -> 16.564356 | ... N41: =IFERROR('Data Sheet'!L31/N36,0) -> 0
B42: Dividned Payout ratio | D42: =IFERROR(D41/D38,0) -> 0.066223723 | E42: =IFERROR(E41/E38,0) -> 0.077646097 | F42: =IFERROR(F41/F38,0) -> 0.07735977 | G42: =IFERROR(G41/G38,0) -> 0.081583394 | H42: =IFERROR(H41/H38,0) -> 0.090172095 | I42: =IFERROR(I41/I38,0) -> 0.079836233 | J42: =IFERROR(J41/J38,0) -> 0.096113744 | K42: =IFERROR(K41/K38,0) -> 0.080120684 | ... N42: =IFERROR(N41/N38,0) -> 0
B44: retained earning | D44: =IFERROR(IF(D41<D38,1-D42,0),0) -> 0.93377628 | E44: =IFERROR(IF(E41<E38,1-E42,0),0) -> 0.9223539 | F44: =IFERROR(IF(F41<F38,1-F42,0),0) -> 0.92264023 | G44: =IFERROR(IF(G41<G38,1-G42,0),0) -> 0.91841661 | H44: =IFERROR(IF(H41<H38,1-H42,0),0) -> 0.9098279 | I44: =IFERROR(IF(I41<I38,1-I42,0),0) -> 0.92016377 | J44: =IFERROR(IF(J41<J38,1-J42,0),0) -> 0.90388626 | K44: =IFERROR(IF(K41<K38,1-K42,0),0) -> 0.91987932 | ... N44: =IFERROR(IF(N41<N38,1-N42,0),0) -> 0
A46: # | B46: Balance Sheet
B47: Equity Share Capital | D47: =IFERROR('Data Sheet'!B57,0) -> 10.14 | E47: =IFERROR('Data Sheet'!C57,0) -> 10.14 | F47: =IFERROR('Data Sheet'!D57,0) -> 10.14 | G47: =IFERROR('Data Sheet'!E57,0) -> 10.14 | H47: =IFERROR('Data Sheet'!F57,0) -> 10.14 | I47: =IFERROR('Data Sheet'!G57,0) -> 10.14 | J47: =IFERROR('Data Sheet'!H57,0) -> 10.14 | K47: =IFERROR('Data Sheet'!I57,0) -> 10.14 | ... N47: =IFERROR('Data Sheet'!L57,0) -> 0
B48: Reserves | D48: =IFERROR('Data Sheet'!B58,0) -> 356.43 | E48: =IFERROR('Data Sheet'!C58,0) -> 412.37 | F48: =IFERROR('Data Sheet'!D58,0) -> 464.31 | G48: =IFERROR('Data Sheet'!E58,0) -> 506.96 | H48: =IFERROR('Data Sheet'!F58,0) -> 559.47 | I48: =IFERROR('Data Sheet'!G58,0) -> 595.37 | J48: =IFERROR('Data Sheet'!H58,0) -> 659.74 | K48: =IFERROR('Data Sheet'!I58,0) -> 726.6 | ... N48: =IFERROR('Data Sheet'!L58,0) -> 0
B49: Borrowings | D49: =IFERROR('Data Sheet'!B59,0) -> 0 | E49: =IFERROR('Data Sheet'!C59,0) -> 0 | F49: =IFERROR('Data Sheet'!D59,0) -> 0 | G49: =IFERROR('Data Sheet'!E59,0) -> 0 | H49: =IFERROR('Data Sheet'!F59,0) -> 1.19 | I49: =IFERROR('Data Sheet'!G59,0) -> 1.44 | J49: =IFERROR('Data Sheet'!H59,0) -> 1.23 | K49: =IFERROR('Data Sheet'!I59,0) -> 0.81 | ... N49: =IFERROR('Data Sheet'!L59,0) -> 0
B50: Other Liabilities | D50: =IFERROR('Data Sheet'!B60,0) -> 113.36 | E50: =IFERROR('Data Sheet'!C60,0) -> 113.63 | F50: =IFERROR('Data Sheet'!D60,0) -> 124.46 | G50: =IFERROR('Data Sheet'!E60,0) -> 141.28 | H50: =IFERROR('Data Sheet'!F60,0) -> 148.04 | I50: =IFERROR('Data Sheet'!G60,0) -> 186.9 | J50: =IFERROR('Data Sheet'!H60,0) -> 193.57 | K50: =IFERROR('Data Sheet'!I60,0) -> 196.12 | ... N50: =IFERROR('Data Sheet'!L60,0) -> 0
B51: Total Liabilities | D51: =IFERROR('Data Sheet'!B61,0) -> 479.93 | E51: =IFERROR('Data Sheet'!C61,0) -> 536.14 | F51: =IFERROR('Data Sheet'!D61,0) -> 598.91 | G51: =IFERROR('Data Sheet'!E61,0) -> 658.38 | H51: =IFERROR('Data Sheet'!F61,0) -> 718.84 | I51: =IFERROR('Data Sheet'!G61,0) -> 793.85 | J51: =IFERROR('Data Sheet'!H61,0) -> 864.68 | K51: =IFERROR('Data Sheet'!I61,0) -> 933.67 | ... N51: =IFERROR('Data Sheet'!L61,0) -> 0
B53: Net Block | D53: =IFERROR('Data Sheet'!B62,0) -> 112.46 | E53: =IFERROR('Data Sheet'!C62,0) -> 106.73 | F53: =IFERROR('Data Sheet'!D62,0) -> 100.73 | G53: =IFERROR('Data Sheet'!E62,0) -> 94.55 | H53: =IFERROR('Data Sheet'!F62,0) -> 97.61 | I53: =IFERROR('Data Sheet'!G62,0) -> 91.29 | J53: =IFERROR('Data Sheet'!H62,0) -> 86.66 | K53: =IFERROR('Data Sheet'!I62,0) -> 91.21 | ... N53: =IFERROR('Data Sheet'!L62,0) -> 0
B54: Capital Work in Progress | D54: =IFERROR('Data Sheet'!B63,0) -> 0.49 | E54: =IFERROR('Data Sheet'!C63,0) -> 0.33 | F54: =IFERROR('Data Sheet'!D63,0) -> 0.94 | G54: =IFERROR('Data Sheet'!E63,0) -> 3.44 | H54: =IFERROR('Data Sheet'!F63,0) -> 1.89 | I54: =IFERROR('Data Sheet'!G63,0) -> 2.47 | J54: =IFERROR('Data Sheet'!H63,0) -> 12.69 | K54: =IFERROR('Data Sheet'!I63,0) -> 9.24 | ... N54: =IFERROR('Data Sheet'!L63,0) -> 0
B55: Investments | D55: =IFERROR('Data Sheet'!B64,0) -> 0 | E55: =IFERROR('Data Sheet'!C64,0) -> 0 | F55: =IFERROR('Data Sheet'!D64,0) -> 0 | G55: =IFERROR('Data Sheet'!E64,0) -> 0 | H55: =IFERROR('Data Sheet'!F64,0) -> 0 | I55: =IFERROR('Data Sheet'!G64,0) -> 0 | J55: =IFERROR('Data Sheet'!H64,0) -> 0 | K55: =IFERROR('Data Sheet'!I64,0) -> 0 | ... N55: =IFERROR('Data Sheet'!L64,0) -> 0
B56: Other Assets | D56: =IFERROR('Data Sheet'!B65-SUM('Data Sheet'!B67:B69),0) -> 85.57 | E56: =IFERROR('Data Sheet'!C65-SUM('Data Sheet'!C67:C69),0) -> 137.24 | F56: =IFERROR('Data Sheet'!D65-SUM('Data Sheet'!D67:D69),0) -> 148.68 | G56: =IFERROR('Data Sheet'!E65-SUM('Data Sheet'!E67:E69),0) -> 321.16 | H56: =IFERROR('Data Sheet'!F65-SUM('Data Sheet'!F67:F69),0) -> 319.74 | I56: =IFERROR('Data Sheet'!G65-SUM('Data Sheet'!G67:G69),0) -> 318.46 | J56: =IFERROR('Data Sheet'!H65-SUM('Data Sheet'!H67:H69),0) -> 221.27 | K56: =IFERROR('Data Sheet'!I65-SUM('Data Sheet'!I67:I69),0) -> 123.43 | ... M56: =IFERROR('Data Sheet'!K65-SUM('Data Sheet'!K67:K69),0) -> 153.73 | N56: =IFERROR('Data Sheet'!L65,0) -> 0
B57: Total non current assets | D57: =IFERROR(SUM(D53:D56),0) -> 198.52 | E57: =IFERROR(SUM(E53:E56),0) -> 244.3 | F57: =IFERROR(SUM(F53:F56),0) -> 250.35 | G57: =IFERROR(SUM(G53:G56),0) -> 419.15 | H57: =IFERROR(SUM(H53:H56),0) -> 419.24 | I57: =IFERROR(SUM(I53:I56),0) -> 412.22 | J57: =IFERROR(SUM(J53:J56),0) -> 320.62 | K57: =IFERROR(SUM(K53:K56),0) -> 223.88 | ... M57: =IFERROR(SUM(M53:M56),0) -> 268.44 | N57: =IFERROR('Data Sheet'!L66,0) -> 0
B59: Receivables | D59: =IFERROR('Data Sheet'!B67,0) -> 33.64 | E59: =IFERROR('Data Sheet'!C67,0) -> 26.38 | F59: =IFERROR('Data Sheet'!D67,0) -> 63.6 | G59: =IFERROR('Data Sheet'!E67,0) -> 63.69 | H59: =IFERROR('Data Sheet'!F67,0) -> 49.53 | I59: =IFERROR('Data Sheet'!G67,0) -> 82.3 | J59: =IFERROR('Data Sheet'!H67,0) -> 87.11 | K59: =IFERROR('Data Sheet'!I67,0) -> 70.84 | ... N59: =IFERROR('Data Sheet'!L67,0) -> 0
B60: Inventory | D60: =IFERROR('Data Sheet'!B68,0) -> 92.32 | E60: =IFERROR('Data Sheet'!C68,0) -> 123.32 | F60: =IFERROR('Data Sheet'!D68,0) -> 93.13 | G60: =IFERROR('Data Sheet'!E68,0) -> 114.58 | H60: =IFERROR('Data Sheet'!F68,0) -> 214.59 | I60: =IFERROR('Data Sheet'!G68,0) -> 163.37 | J60: =IFERROR('Data Sheet'!H68,0) -> 179.62 | K60: =IFERROR('Data Sheet'!I68,0) -> 170.48 | ... N60: =IFERROR('Data Sheet'!L68,0) -> 0
B61: Cash & Bank | D61: =IFERROR('Data Sheet'!B69,0) -> 155.45 | E61: =IFERROR('Data Sheet'!C69,0) -> 142.14 | F61: =IFERROR('Data Sheet'!D69,0) -> 191.83 | G61: =IFERROR('Data Sheet'!E69,0) -> 60.96 | H61: =IFERROR('Data Sheet'!F69,0) -> 35.48 | I61: =IFERROR('Data Sheet'!G69,0) -> 135.96 | J61: =IFERROR('Data Sheet'!H69,0) -> 277.33 | K61: =IFERROR('Data Sheet'!I69,0) -> 468.47 | ... N61: =IFERROR('Data Sheet'!L69,0) -> 0
B62: total current Assets | D62: =IFERROR(SUM(D59:D61),0) -> 281.41 | E62: =IFERROR(SUM(E59:E61),0) -> 291.84 | F62: =IFERROR(SUM(F59:F61),0) -> 348.56 | G62: =IFERROR(SUM(G59:G61),0) -> 239.23 | H62: =IFERROR(SUM(H59:H61),0) -> 299.6 | I62: =IFERROR(SUM(I59:I61),0) -> 381.63 | J62: =IFERROR(SUM(J59:J61),0) -> 544.06 | K62: =IFERROR(SUM(K59:K61),0) -> 709.79 | ... N62: =IFERROR(SUM(N59:N61),0) -> 0
B64: total assets | D64: =IFERROR(SUM(D62,D57),0) -> 479.93 | E64: =IFERROR(SUM(E62,E57),0) -> 536.14 | F64: =IFERROR(SUM(F62,F57),0) -> 598.91 | G64: =IFERROR(SUM(G62,G57),0) -> 658.38 | H64: =IFERROR(SUM(H62,H57),0) -> 718.84 | I64: =IFERROR(SUM(I62,I57),0) -> 793.85 | J64: =IFERROR(SUM(J62,J57),0) -> 864.68 | K64: =IFERROR(SUM(K62,K57),0) -> 933.67 | ... M64: =IFERROR(SUM(M62,M57),0) -> 1057.58
B66: check | D66: =D64=D51 -> TRUE | E66: =E64=E51 -> TRUE | F66: =F64=F51 -> TRUE | G66: =G64=G51 -> TRUE | H66: =H64=H51 -> TRUE | I66: =I64=I51 -> TRUE | J66: =J64=J51 -> TRUE | K66: =K64=K51 -> TRUE | ... M66: =M64=M51 -> TRUE
A69: # | B69: Cash flow statement
B70: Operating Activities
B71: Profit from operations | D71: =IFERROR('Cash Flow Data'!E4,0) -> 91 | E71: =IFERROR('Cash Flow Data'!F4,0) -> 97 | F71: =IFERROR('Cash Flow Data'!G4,0) -> 103 | G71: =IFERROR('Cash Flow Data'!H4,0) -> 93 | H71: =IFERROR('Cash Flow Data'!I4,0) -> 95 | I71: =IFERROR('Cash Flow Data'!J4,0) -> 72 | J71: =IFERROR('Cash Flow Data'!K4,0) -> 108 | K71: =IFERROR('Cash Flow Data'!L4,0) -> 137 | ... M71: =IFERROR('Cash Flow Data'!N4,0) -> 97
B72: Receivables | D72: =IFERROR('Cash Flow Data'!E5,0) -> 4 | E72: =IFERROR('Cash Flow Data'!F5,0) -> 5 | F72: =IFERROR('Cash Flow Data'!G5,0) -> -38 | G72: =IFERROR('Cash Flow Data'!H5,0) -> -1 | H72: =IFERROR('Cash Flow Data'!I5,0) -> 14 | I72: =IFERROR('Cash Flow Data'!J5,0) -> -32 | J72: =IFERROR('Cash Flow Data'!K5,0) -> -6 | K72: =IFERROR('Cash Flow Data'!L5,0) -> 15 | ... M72: =IFERROR('Cash Flow Data'!N5,0) -> -68
B73: Inventory | D73: =IFERROR('Cash Flow Data'!E6,0) -> 29 | E73: =IFERROR('Cash Flow Data'!F6,0) -> -24 | F73: =IFERROR('Cash Flow Data'!G6,0) -> 30 | G73: =IFERROR('Cash Flow Data'!H6,0) -> -21 | H73: =IFERROR('Cash Flow Data'!I6,0) -> -100 | I73: =IFERROR('Cash Flow Data'!J6,0) -> 51 | J73: =IFERROR('Cash Flow Data'!K6,0) -> -16 | K73: =IFERROR('Cash Flow Data'!L6,0) -> 9 | ... M73: =IFERROR('Cash Flow Data'!N6,0) -> 17
B74: Payables | D74: =IFERROR('Cash Flow Data'!E7,0) -> -6 | E74: =IFERROR('Cash Flow Data'!F7,0) -> 12 | F74: =IFERROR('Cash Flow Data'!G7,0) -> 5 | G74: =IFERROR('Cash Flow Data'!H7,0) -> 8 | H74: =IFERROR('Cash Flow Data'!I7,0) -> 5 | I74: =IFERROR('Cash Flow Data'!J7,0) -> 27 | J74: =IFERROR('Cash Flow Data'!K7,0) -> 3 | K74: =IFERROR('Cash Flow Data'!L7,0) -> -23 | ... M74: =IFERROR('Cash Flow Data'!N7,0) -> -18
B75: Loans Advances | D75: =IFERROR('Cash Flow Data'!E8,0) -> -1 | E75: =IFERROR('Cash Flow Data'!F8,0) -> 0 | F75: =IFERROR('Cash Flow Data'!G8,0) -> 0 | G75: =IFERROR('Cash Flow Data'!H8,0) -> 0 | H75: =IFERROR('Cash Flow Data'!I8,0) -> 0 | I75: =IFERROR('Cash Flow Data'!J8,0) -> 0 | J75: =IFERROR('Cash Flow Data'!K8,0) -> 0 | K75: =IFERROR('Cash Flow Data'!L8,0) -> 0 | ... M75: =IFERROR('Cash Flow Data'!N8,0) -> 0
B76: Other WC items | D76: =IFERROR('Cash Flow Data'!E9,0) -> 9 | E76: =IFERROR('Cash Flow Data'!F9,0) -> -13 | F76: =IFERROR('Cash Flow Data'!G9,0) -> -8 | G76: =IFERROR('Cash Flow Data'!H9,0) -> -19 | H76: =IFERROR('Cash Flow Data'!I9,0) -> -6 | I76: =IFERROR('Cash Flow Data'!J9,0) -> 52 | J76: =IFERROR('Cash Flow Data'!K9,0) -> -25 | K76: =IFERROR('Cash Flow Data'!L9,0) -> 75 | ... M76: =IFERROR('Cash Flow Data'!N9,0) -> 26
B77: Working capital changes | D77: =IFERROR('Cash Flow Data'!E10,0) -> 34 | E77: =IFERROR('Cash Flow Data'!F10,0) -> -20 | F77: =IFERROR('Cash Flow Data'!G10,0) -> -10 | G77: =IFERROR('Cash Flow Data'!H10,0) -> -34 | H77: =IFERROR('Cash Flow Data'!I10,0) -> -87 | I77: =IFERROR('Cash Flow Data'!J10,0) -> 98 | J77: =IFERROR('Cash Flow Data'!K10,0) -> -44 | K77: =IFERROR('Cash Flow Data'!L10,0) -> 77 | ... M77: =IFERROR('Cash Flow Data'!N10,0) -> -43
B78: Direct taxes | D78: =IFERROR('Cash Flow Data'!E11,0) -> -25 | E78: =IFERROR('Cash Flow Data'!F11,0) -> -37 | F78: =IFERROR('Cash Flow Data'!G11,0) -> -38 | G78: =IFERROR('Cash Flow Data'!H11,0) -> -35 | H78: =IFERROR('Cash Flow Data'!I11,0) -> -30 | I78: =IFERROR('Cash Flow Data'!J11,0) -> -18 | J78: =IFERROR('Cash Flow Data'!K11,0) -> -27 | K78: =IFERROR('Cash Flow Data'!L11,0) -> -39 | ... M78: =IFERROR('Cash Flow Data'!N11,0) -> -32
B79: Other operating items | D79: =IFERROR('Cash Flow Data'!E12,0) -> 0 | E79: =IFERROR('Cash Flow Data'!F12,0) -> 0 | F79: =IFERROR('Cash Flow Data'!G12,0) -> 0 | G79: =IFERROR('Cash Flow Data'!H12,0) -> -4 | H79: =IFERROR('Cash Flow Data'!I12,0) -> 4 | I79: =IFERROR('Cash Flow Data'!J12,0) -> 0 | J79: =IFERROR('Cash Flow Data'!K12,0) -> 0 | K79: =IFERROR('Cash Flow Data'!L12,0) -> -18 | ... M79: =IFERROR('Cash Flow Data'!N12,0) -> 0
B80: cash from operating activities | D80: =IFERROR(SUM(D71:D79),0) -> 135 | E80: =IFERROR(SUM(E71:E79),0) -> 20 | F80: =IFERROR(SUM(F71:F79),0) -> 44 | G80: =IFERROR(SUM(G71:G79),0) -> -13 | H80: =IFERROR(SUM(H71:H79),0) -> -105 | I80: =IFERROR(SUM(I71:I79),0) -> 250 | J80: =IFERROR(SUM(J71:J79),0) -> -7 | K80: =IFERROR(SUM(K71:K79),0) -> 233 | ... M80: =IFERROR(SUM(M71:M79),0) -> -21
B82: Investing Activities
B83: Fixed assets purchased | D83: =IFERROR('Cash Flow Data'!E14,0) -> -13 | E83: =IFERROR('Cash Flow Data'!F14,0) -> -13 | F83: =IFERROR('Cash Flow Data'!G14,0) -> -16 | G83: =IFERROR('Cash Flow Data'!H14,0) -> -18 | H83: =IFERROR('Cash Flow Data'!I14,0) -> -22 | I83: =IFERROR('Cash Flow Data'!J14,0) -> -15 | J83: =IFERROR('Cash Flow Data'!K14,0) -> -17 | K83: =IFERROR('Cash Flow Data'!L14,0) -> -30 | ... M83: =IFERROR('Cash Flow Data'!N14,0) -> -41
B84: Fixed assets sold | D84: =IFERROR('Cash Flow Data'!E15,0) -> 2 | E84: =IFERROR('Cash Flow Data'!F15,0) -> 0 | F84: =IFERROR('Cash Flow Data'!G15,0) -> 0 | G84: =IFERROR('Cash Flow Data'!H15,0) -> 1 | H84: =IFERROR('Cash Flow Data'!I15,0) -> 1 | I84: =IFERROR('Cash Flow Data'!J15,0) -> 1 | J84: =IFERROR('Cash Flow Data'!K15,0) -> 1 | K84: =IFERROR('Cash Flow Data'!L15,0) -> 1 | ... M84: =IFERROR('Cash Flow Data'!N15,0) -> 1
B85: Interest received | D85: =IFERROR('Cash Flow Data'!E16,0) -> 6 | E85: =IFERROR('Cash Flow Data'!F16,0) -> 11 | F85: =IFERROR('Cash Flow Data'!G16,0) -> 9 | G85: =IFERROR('Cash Flow Data'!H16,0) -> 18 | H85: =IFERROR('Cash Flow Data'!I16,0) -> 16 | I85: =IFERROR('Cash Flow Data'!J16,0) -> 13 | J85: =IFERROR('Cash Flow Data'!K16,0) -> 12 | K85: =IFERROR('Cash Flow Data'!L16,0) -> 11 | ... M85: =IFERROR('Cash Flow Data'!N16,0) -> 34
B86: Redemp n Canc of Shares | D86: =IFERROR('Cash Flow Data'!E17,0) -> 0 | E86: =IFERROR('Cash Flow Data'!F17,0) -> 0 | F86: =IFERROR('Cash Flow Data'!G17,0) -> 0 | G86: =IFERROR('Cash Flow Data'!H17,0) -> 0 | H86: =IFERROR('Cash Flow Data'!I17,0) -> 0 | I86: =IFERROR('Cash Flow Data'!J17,0) -> 160 | J86: =IFERROR('Cash Flow Data'!K17,0) -> 160 | K86: =IFERROR('Cash Flow Data'!L17,0) -> 0 | ... M86: =IFERROR('Cash Flow Data'!N17,0) -> 0
B87: Acquisition of companies | D87: =IFERROR('Cash Flow Data'!E18,0) -> 0 | E87: =IFERROR('Cash Flow Data'!F18,0) -> 0 | F87: =IFERROR('Cash Flow Data'!G18,0) -> 0 | G87: =IFERROR('Cash Flow Data'!H18,0) -> -160 | H87: =IFERROR('Cash Flow Data'!I18,0) -> 0 | I87: =IFERROR('Cash Flow Data'!J18,0) -> -160 | J87: =IFERROR('Cash Flow Data'!K18,0) -> 0 | K87: =IFERROR('Cash Flow Data'!L18,0) -> 0 | ... M87: =IFERROR('Cash Flow Data'!N18,0) -> 0
B88: Other investing items | D88: =IFERROR('Cash Flow Data'!E19,0) -> -81 | E88: =IFERROR('Cash Flow Data'!F19,0) -> -12 | F88: =IFERROR('Cash Flow Data'!G19,0) -> -59 | G88: =IFERROR('Cash Flow Data'!H19,0) -> 147 | H88: =IFERROR('Cash Flow Data'!I19,0) -> 53 | I88: =IFERROR('Cash Flow Data'!J19,0) -> -91 | J88: =IFERROR('Cash Flow Data'!K19,0) -> -140 | K88: =IFERROR('Cash Flow Data'!L19,0) -> -131 | ... M88: =IFERROR('Cash Flow Data'!N19,0) -> -63
B89: cash from Investing Activities | D89: =SUM(D83:D88) -> -86 | E89: =SUM(E83:E88) -> -14 | F89: =SUM(F83:F88) -> -66 | G89: =SUM(G83:G88) -> -12 | H89: =SUM(H83:H88) -> 48 | I89: =SUM(I83:I88) -> -92 | J89: =SUM(J83:J88) -> 16 | K89: =SUM(K83:K88) -> -149 | ... M89: =SUM(M83:M88) -> -69
B91: Financing Activities
B92: Interest paid fin | D92: =IFERROR('Cash Flow Data'!E21,0) -> 0 | E92: =IFERROR('Cash Flow Data'!F21,0) -> -0.4 | F92: =IFERROR('Cash Flow Data'!G21,0) -> -0.24 | G92: =IFERROR('Cash Flow Data'!H21,0) -> -0.12 | H92: =IFERROR('Cash Flow Data'!I21,0) -> -0.3 | I92: =IFERROR('Cash Flow Data'!J21,0) -> -0.28 | J92: =IFERROR('Cash Flow Data'!K21,0) -> -0.35 | K92: =IFERROR('Cash Flow Data'!L21,0) -> -0.44 | ... M92: =IFERROR('Cash Flow Data'!N21,0) -> -0.41
B93: Dividends paid | D93: =IFERROR('Cash Flow Data'!E22,0) -> -6.09 | E93: =IFERROR('Cash Flow Data'!F22,0) -> -6.09 | F93: =IFERROR('Cash Flow Data'!G22,0) -> -7.61 | G93: =IFERROR('Cash Flow Data'!H22,0) -> -9.13 | H93: =IFERROR('Cash Flow Data'!I22,0) -> -10.14 | I93: =IFERROR('Cash Flow Data'!J22,0) -> -12.68 | J93: =IFERROR('Cash Flow Data'!K22,0) -> -10.14 | K93: =IFERROR('Cash Flow Data'!L22,0) -> -15.21 | ... M93: =IFERROR('Cash Flow Data'!N22,0) -> -27.78
B94: Financial liabilities | D94: =IFERROR('Cash Flow Data'!E23,0) -> 0 | E94: =IFERROR('Cash Flow Data'!F23,0) -> 0 | F94: =IFERROR('Cash Flow Data'!G23,0) -> 0 | G94: =IFERROR('Cash Flow Data'!H23,0) -> 0 | H94: =IFERROR('Cash Flow Data'!I23,0) -> -0.59 | I94: =IFERROR('Cash Flow Data'!J23,0) -> -0.63 | J94: =IFERROR('Cash Flow Data'!K23,0) -> -0.8 | K94: =IFERROR('Cash Flow Data'!L23,0) -> -0.55 | ... M94: =IFERROR('Cash Flow Data'!N23,0) -> -0.26
B95: Other financing items | D95: =IFERROR('Cash Flow Data'!E24,0) -> -1.24 | E95: =IFERROR('Cash Flow Data'!F24,0) -> -1.24 | F95: =IFERROR('Cash Flow Data'!G24,0) -> -1.55 | G95: =IFERROR('Cash Flow Data'!H24,0) -> -1.88 | H95: =IFERROR('Cash Flow Data'!I24,0) -> -2.08 | I95: =IFERROR('Cash Flow Data'!J24,0) -> 0 | J95: =IFERROR('Cash Flow Data'!K24,0) -> 0 | K95: =IFERROR('Cash Flow Data'!L24,0) -> 0 | ... M95: =IFERROR('Cash Flow Data'!N24,0) -> 0
B96: cash from financing activities | D96: =SUM(D92:D95) -> -7.33 | E96: =SUM(E92:E95) -> -7.73 | F96: =SUM(F92:F95) -> -9.4 | G96: =SUM(G92:G95) -> -11.13 | H96: =SUM(H92:H95) -> -13.11 | I96: =SUM(I92:I95) -> -13.59 | J96: =SUM(J92:J95) -> -11.29 | K96: =SUM(K92:K95) -> -16.2 | ... M96: =SUM(M92:M95) -> -28.45
B98: Net cash flow | D98: =IFERROR(D96+D89+D80,0) -> 41.67 | E98: =IFERROR(E96+E89+E80,0) -> -1.73 | F98: =IFERROR(F96+F89+F80,0) -> -31.4 | G98: =IFERROR(G96+G89+G80,0) -> -36.13 | H98: =IFERROR(H96+H89+H80,0) -> -70.11 | I98: =IFERROR(I96+I89+I80,0) -> 144.41 | J98: =IFERROR(J96+J89+J80,0) -> -2.29 | K98: =IFERROR(K96+K89+K80,0) -> 67.8 | ... M98: =IFERROR(M96+M89+M80,0) -> -118.45
B103: directly take the cash flow stmtnt from the data sheet
B105: Cash from Operating Activity | D105: =IFERROR('Data Sheet'!B82,0) -> 101.07 | E105: =IFERROR('Data Sheet'!C82,0) -> 39.88 | F105: =IFERROR('Data Sheet'!D82,0) -> 55 | G105: =IFERROR('Data Sheet'!E82,0) -> 20.59 | H105: =IFERROR('Data Sheet'!F82,0) -> -17.62 | I105: =IFERROR('Data Sheet'!G82,0) -> 151.51 | J105: =IFERROR('Data Sheet'!H82,0) -> 36.9 | K105: =IFERROR('Data Sheet'!I82,0) -> 157.33 | ... M105: =IFERROR('Data Sheet'!K82,0) -> 22.09
B106: Cash from Investing Activity | D106: =IFERROR('Data Sheet'!B83,0) -> -86.38 | E106: =IFERROR('Data Sheet'!C83,0) -> -13.87 | F106: =IFERROR('Data Sheet'!D83,0) -> -65.48 | G106: =IFERROR('Data Sheet'!E83,0) -> -12.66 | H106: =IFERROR('Data Sheet'!F83,0) -> 47.4 | I106: =IFERROR('Data Sheet'!G83,0) -> -92.29 | J106: =IFERROR('Data Sheet'!H83,0) -> 16.01 | K106: =IFERROR('Data Sheet'!I83,0) -> -148.36 | ... M106: =IFERROR('Data Sheet'!K83,0) -> -69.05
B107: Cash from Financing Activity | D107: =IFERROR('Data Sheet'!B84,0) -> -7.32 | E107: =IFERROR('Data Sheet'!C84,0) -> -7.73 | F107: =IFERROR('Data Sheet'!D84,0) -> -9.4 | G107: =IFERROR('Data Sheet'!E84,0) -> -11.13 | H107: =IFERROR('Data Sheet'!F84,0) -> -13.11 | I107: =IFERROR('Data Sheet'!G84,0) -> -13.59 | J107: =IFERROR('Data Sheet'!H84,0) -> -11.29 | K107: =IFERROR('Data Sheet'!I84,0) -> -16.2 | ... M107: =IFERROR('Data Sheet'!K84,0) -> -28.45
B108: Net Cash Flow | D108: =IFERROR('Data Sheet'!B85,0) -> 7.37 | E108: =IFERROR('Data Sheet'!C85,0) -> 18.28 | F108: =IFERROR('Data Sheet'!D85,0) -> -19.88 | G108: =IFERROR('Data Sheet'!E85,0) -> -3.2 | H108: =IFERROR('Data Sheet'!F85,0) -> 16.67 | I108: =IFERROR('Data Sheet'!G85,0) -> 45.63 | J108: =IFERROR('Data Sheet'!H85,0) -> 41.62 | K108: =IFERROR('Data Sheet'!I85,0) -> -7.23 | ... M108: =IFERROR('Data Sheet'!K85,0) -> -75.41

Sheet Ratio Analysis
B2: ="Ratio analysis - "&'Data Sheet'!B1 -> Ratio analysis - HONDA INDIA POWER PRODUCTS LTD
B3: Years | D3: ='Data Sheet'!B16 -> 42460 | E3: ='Data Sheet'!C16 -> 42825 | F3: ='Data Sheet'!D16 -> 43190 | G3: ='Data Sheet'!E16 -> 43555 | H3: ='Data Sheet'!F16 -> 43921 | I3: ='Data Sheet'!G16 -> 44286 | J3: ='Data Sheet'!H16 -> 44651 | K3: ='Data Sheet'!I16 -> 45016 | ... M3: ='Data Sheet'!K16 -> 45747 | N3: Trends | O3: mean | P3: Median
B5: SalesGrowth | E5: =IFERROR(historicalFS!E7,0) -> 0.043058219 | F5: =IFERROR(historicalFS!F7,0) -> 0.094075066 | G5: =IFERROR(historicalFS!G7,0) -> 0.062620474 | H5: =IFERROR(historicalFS!H7,0) -> 0.040152964 | I5: =IFERROR(historicalFS!I7,0) -> 0.10640554 | J5: =IFERROR(historicalFS!J7,0) -> 0.23148444 | K5: =IFERROR(historicalFS!K7,0) -> 0.077835145 | L5: =IFERROR(historicalFS!L7,0) -> -0.20638856 | M5: =IFERROR(historicalFS!M7,0) -> -0.19699313 | O5: =IFERROR(AVERAGE(E5:M5),0) -> 0.028027795 | P5: =IFERROR(MEDIAN(E5:M5),0) -> 0.062620474
B6: EBITDA Growth | E6: =IFERROR((historicalFS!E18-historicalFS!D18)/historicalFS!D18,0) -> 0.068361701 | F6: =IFERROR((historicalFS!F18-historicalFS!E18)/historicalFS!E18,0) -> 0.14161149 | G6: =IFERROR((historicalFS!G18-historicalFS!F18)/historicalFS!F18,0) -> 0.0058576925 | H6: =IFERROR((historicalFS!H18-historicalFS!G18)/historicalFS!G18,0) -> 0.0694833 | I6: =IFERROR((historicalFS!I18-historicalFS!H18)/historicalFS!H18,0) -> -0.11696562 | J6: =IFERROR((historicalFS!J18-historicalFS!I18)/historicalFS!I18,0) -> 0.22864398 | K6: =IFERROR((historicalFS!K18-historicalFS!J18)/historicalFS!J18,0) -> 0.28204497 | L6: =IFERROR((historicalFS!L18-historicalFS!K18)/historicalFS!K18,0) -> -0.30163116 | M6: =IFERROR((historicalFS!M18-historicalFS!L18)/historicalFS!L18,0) -> -0.015607826 | O6: =IFERROR(AVERAGE(E6:M6),0) -> 0.040199835 | P6: =IFERROR(MEDIAN(E6:M6),0) -> 0.068361701
B7: EBIT Growth | E7: =IFERROR(historicalFS!E27/historicalFS!D27-1,0) -> 0.086065227 | F7: =IFERROR(historicalFS!F27/historicalFS!E27-1,0) -> 0.17736526 | G7: =IFERROR(historicalFS!G27/historicalFS!F27-1,0) -> 0.016561775 | H7: =IFERROR(historicalFS!H27/historicalFS!G27-1,0) -> 0.07220593 | I7: =IFERROR(historicalFS!I27/historicalFS!H27-1,0) -> -0.12186227 | J7: =IFERROR(historicalFS!J27/historicalFS!I27-1,0) -> 0.27200997 | K7: =IFERROR(historicalFS!K27/historicalFS!J27-1,0) -> 0.30112091 | L7: =IFERROR(historicalFS!L27/historicalFS!K27-1,0) -> -0.32581967 | M7: =IFERROR(historicalFS!M27/historicalFS!L27-1,0) -> -0.027355623 | O7: =IFERROR(AVERAGE(E7:M7),0) -> 0.050032388 | P7: =IFERROR(MEDIAN(E7:M7),0) -> 0.07220593
B8: Net Profit Growth | E8: =IFERROR(historicalFS!E33/historicalFS!D33-1,0) -> 0.066114802 | F8: =IFERROR(historicalFS!F33/historicalFS!E33-1,0) -> 0.20576216 | G8: =IFERROR(historicalFS!G33/historicalFS!F33-1,0) -> 0.053126589 | H8: =IFERROR(historicalFS!H33/historicalFS!G33-1,0) -> 0.13138627 | I8: =IFERROR(historicalFS!I33/historicalFS!H33-1,0) -> -0.096785663 | J8: =IFERROR(historicalFS!J33/historicalFS!I33-1,0) -> 0.24596488 | K8: =IFERROR(historicalFS!K33/historicalFS!J33-1,0) -> 0.31949447 | L8: =IFERROR(historicalFS!L33/historicalFS!K33-1,0) -> -0.37890906 | M8: =IFERROR(historicalFS!M33/historicalFS!L33-1,0) -> -0.0050119516 | O8: =IFERROR(AVERAGE(E8:M8),0) -> 0.060126945 | P8: =IFERROR(MEDIAN(E8:M8),0) -> 0.066114802 | R8: ebit margin is sasme as operating margin
B9: Dividend Growth | E9: =IFERROR(historicalFS!E41/historicalFS!D41-1,0) -> 0.25 | F9: =IFERROR(historicalFS!F41/historicalFS!E41-1,0) -> 0.20131579 | G9: =IFERROR(historicalFS!G41/historicalFS!F41-1,0) -> 0.11062432 | H9: =IFERROR(historicalFS!H41/historicalFS!G41-1,0) -> 0.2504931 | I9: =IFERROR(historicalFS!I41/historicalFS!H41-1,0) -> -0.20031546 | J9: =IFERROR(historicalFS!J41/historicalFS!I41-1,0) -> 0.5 | K9: =IFERROR(historicalFS!K41/historicalFS!J41-1,0) -> 0.099934254 | L9: =IFERROR(historicalFS!L41/historicalFS!K41-1,0) -> 0.060370592 | M9: =IFERROR(historicalFS!M41/historicalFS!L41-1,0) -> 0.22886133 | O9: =IFERROR(AVERAGE(E9:M9),0) -> 0.16680932 | P9: =IFERROR(MEDIAN(E9:M9),0) -> 0.20131579
B11: Gross Margin | D11: =IFERROR(historicalFS!D13,0) -> 0.39146267 | E11: =IFERROR(historicalFS!E13,0) -> 0.38513494 | F11: =IFERROR(historicalFS!F13,0) -> 0.38555613 | G11: =IFERROR(historicalFS!G13,0) -> 0.36348483 | H11: =IFERROR(historicalFS!H13,0) -> 0.3820937 | I11: =IFERROR(historicalFS!I13,0) -> 0.33296057 | J11: =IFERROR(historicalFS!J13,0) -> 0.3479404 | K11: =IFERROR(historicalFS!K13,0) -> 0.37506519 | ... M11: =IFERROR(historicalFS!M13,0) -> 0.41572341 | O11: =IFERROR(AVERAGE(D11:M11),0) -> 0.37491732 | P11: =IFERROR(MEDIAN(D11:M11),0) -> 0.37857945
B12: EBITDA margin | D12: =IFERROR(historicalFS!D19,0) -> 0.21219958 | E12: =IFERROR(historicalFS!E19,0) -> 0.21734732 | F12: =IFERROR(historicalFS!F19,0) -> 0.22679083 | G12: =IFERROR(historicalFS!G19,0) -> 0.21467618 | H12: =IFERROR(historicalFS!H19,0) -> 0.22072964 | I12: =IFERROR(historicalFS!I19,0) -> 0.17616674 | J12: =IFERROR(historicalFS!J19,0) -> 0.17576041 | K12: =IFERROR(historicalFS!K19,0) -> 0.20906049 | ... M12: =IFERROR(historicalFS!M19,0) -> 0.22552661 | O12: =IFERROR(AVERAGE(D12:M12),0) -> 0.20622286 | P12: =IFERROR(MEDIAN(D12:M12),0) -> 0.21343788
B13: EBIT Margin | D13: =IFERROR((historicalFS!D18-historicalFS!D24)/historicalFS!D6,0) -> 0.17679583 | E13: =IFERROR((historicalFS!E18-historicalFS!E24)/historicalFS!E6,0) -> 0.18393229 | F13: =IFERROR((historicalFS!F18-historicalFS!F24)/historicalFS!F6,0) -> 0.1974733 | G13: =IFERROR((historicalFS!G18-historicalFS!G24)/historicalFS!G6,0) -> 0.18877776 | H13: =IFERROR((historicalFS!H18-historicalFS!H24)/historicalFS!H6,0) -> 0.19471154 | I13: =IFERROR((historicalFS!I18-historicalFS!I24)/historicalFS!I6,0) -> 0.15458922 | J13: =IFERROR((historicalFS!J18-historicalFS!J24)/historicalFS!J6,0) -> 0.15974366 | K13: =IFERROR((historicalFS!K18-historicalFS!K24)/historicalFS!K6,0) -> 0.192387 | ... M13: =IFERROR((historicalFS!M18-historicalFS!M24)/historicalFS!M6,0) -> 0.19807864 | O13: =IFERROR(AVERAGE(D13:M13),0) -> 0.18100166 | P13: =IFERROR(MEDIAN(D13:M13),0) -> 0.18635502
B14: EBT Margin | D14: =IFERROR(historicalFS!D28,0) -> 0.17545815 | E14: =IFERROR(historicalFS!E28,0) -> 0.18269258 | F14: =IFERROR(historicalFS!F28,0) -> 0.19660068 | G14: =IFERROR(historicalFS!G28,0) -> 0.18807913 | H14: =IFERROR(historicalFS!H28,0) -> 0.19387491 | I14: =IFERROR(historicalFS!I28,0) -> 0.15387565 | J14: =IFERROR(historicalFS!J28,0) -> 0.15893937 | K14: =IFERROR(historicalFS!K28,0) -> 0.19186546 | ... M14: =IFERROR(historicalFS!M28,0) -> 0.19742392 | O14: =IFERROR(AVERAGE(D14:M14),0) -> 0.18018013 | P14: =IFERROR(MEDIAN(D14:M14),0) -> 0.18538586
B15: Net Profit Margin | D15: =IFERROR(historicalFS!D34,0) -> 0.13645754 | E15: =IFERROR(historicalFS!E34,0) -> 0.13947391 | F15: =IFERROR(historicalFS!F34,0) -> 0.1537119 | G15: =IFERROR(historicalFS!G34,0) -> 0.15233858 | H15: =IFERROR(historicalFS!H34,0) -> 0.16570041 | I15: =IFERROR(historicalFS!I34,0) -> 0.13526956 | J15: =IFERROR(historicalFS!J34,0) -> 0.13686013 | K15: =IFERROR(historicalFS!K34,0) -> 0.16754527 | ... M15: =IFERROR(historicalFS!M34,0) -> 0.16247183 | O15: =IFERROR(AVERAGE(D15:M15),0) -> 0.14809523 | P15: =IFERROR(MEDIAN(D15:M15),0) -> 0.14590624
B17: Sales Expenses%sales | D17: =IFERROR(historicalFS!D16,0) -> 0.17926309 | E17: =IFERROR(historicalFS!E16,0) -> 0.16778763 | F17: =IFERROR(historicalFS!F16,0) -> 0.1587653 | G17: =IFERROR(historicalFS!G16,0) -> 0.14880865 | H17: =IFERROR(historicalFS!H16,0) -> 0.16136406 | I17: =IFERROR(historicalFS!I16,0) -> 0.15679383 | J17: =IFERROR(historicalFS!J16,0) -> 0.17217999 | K17: =IFERROR(historicalFS!K16,0) -> 0.1660047 | ... M17: =IFERROR(historicalFS!M16,0) -> 0.19019679 | O17: =IFERROR(AVERAGE(D17:M17),0) -> 0.16869446 | P17: =IFERROR(MEDIAN(D17:M17),0) -> 0.16689616
B18: Deprication%sales | D18: =IFERROR(historicalFS!D25,0) -> 0.035403754 | E18: =IFERROR(historicalFS!E25,0) -> 0.03341503 | F18: =IFERROR(historicalFS!F25,0) -> 0.029317531 | G18: =IFERROR(historicalFS!G25,0) -> 0.025898416 | H18: =IFERROR(historicalFS!H25,0) -> 0.0260181 | I18: =IFERROR(historicalFS!I25,0) -> 0.021577524 | J18: =IFERROR(historicalFS!J25,0) -> 0.016016743 | K18: =IFERROR(historicalFS!K25,0) -> 0.016673487 | ... M18: =IFERROR(historicalFS!M25,0) -> 0.027447968 | O18: =IFERROR(AVERAGE(D18:M18),0) -> 0.0252212 | P18: =IFERROR(MEDIAN(D18:M18),0) -> 0.025958258
B19: OperatingIncome%sales | D19: =D13 -> 0.17679583 | E19: =E13 -> 0.18393229 | F19: =F13 -> 0.1974733 | G19: =G13 -> 0.18877776 | H19: =H13 -> 0.19471154 | I19: =I13 -> 0.15458922 | J19: =J13 -> 0.15974366 | K19: =K13 -> 0.192387 | ... M19: =M13 -> 0.19807864 | O19: =IFERROR(AVERAGE(D19:M19),0) -> 0.18100166 | P19: =IFERROR(MEDIAN(D19:M19),0) -> 0.18635502 | S19: operating income % sales is same as EBUIT margin
B21: ROCE | D21: =IFERROR((historicalFS!D18-historicalFS!D24)/SUM(historicalFS!D47:D49,),0) -> 0.32449464 | E21: =IFERROR((historicalFS!E18-historicalFS!E24)/SUM(historicalFS!E47:E49,),0) -> 0.30550756 | F21: =IFERROR((historicalFS!F18-historicalFS!F24)/SUM(historicalFS!F47:F49,),0) -> 0.31957003 | G21: =IFERROR((historicalFS!G18-historicalFS!G24)/SUM(historicalFS!G47:G49,),0) -> 0.29785341 | H21: =IFERROR((historicalFS!H18-historicalFS!H24)/SUM(historicalFS!H47:H49,),0) -> 0.28948844 | I21: =IFERROR((historicalFS!I18-historicalFS!I24)/SUM(historicalFS!I47:I49,),0) -> 0.23914655 | J21: =IFERROR((historicalFS!J18-historicalFS!J24)/SUM(historicalFS!J47:J49,),0) -> 0.27523059 | K21: =IFERROR((historicalFS!K18-historicalFS!K24)/SUM(historicalFS!K47:K49,),0) -> 0.32508982 | ... M21: =IFERROR((historicalFS!M18-historicalFS!M24)/SUM(historicalFS!M47:M49,),0) -> 0.18216134 | O21: =IFERROR(AVERAGE(D21:M21),0) -> 0.27575874 | P21: =IFERROR(MEDIAN(D21:M21),0) -> 0.29367093
B22: Reatined Earning % | D22: =IFERROR(historicalFS!D44,0) -> 0.93377628 | E22: =IFERROR(historicalFS!E44,0) -> 0.9223539 | F22: =IFERROR(historicalFS!F44,0) -> 0.92264023 | G22: =IFERROR(historicalFS!G44,0) -> 0.91841661 | H22: =IFERROR(historicalFS!H44,0) -> 0.9098279 | I22: =IFERROR(historicalFS!I44,0) -> 0.92016377 | J22: =IFERROR(historicalFS!J44,0) -> 0.90388626 | K22: =IFERROR(historicalFS!K44,0) -> 0.91987932 | ... M22: =IFERROR(historicalFS!M44,0) -> 0.83106014 | O22: =IFERROR(AVERAGE(D22:M22),0) -> 0.90452167 | P22: =IFERROR(MEDIAN(D22:M22),0) -> 0.91914796
B23: ROE% | D23: =IFERROR(historicalFS!D33/SUM(historicalFS!D47:D48),0) -> 0.25045694 | E23: =IFERROR(historicalFS!E33/SUM(historicalFS!E47:E48),0) -> 0.23166316 | F23: =IFERROR(historicalFS!F33/SUM(historicalFS!F47:F48),0) -> 0.24875119 | G23: =IFERROR(historicalFS!G33/SUM(historicalFS!G47:G48),0) -> 0.2403597 | H23: =IFERROR(historicalFS!H33/SUM(historicalFS!H47:H48),0) -> 0.24687067 | I23: =IFERROR(historicalFS!I33/SUM(historicalFS!I47:I48),0) -> 0.20975706 | J23: =IFERROR(historicalFS!J33/SUM(historicalFS!J47:J48),0) -> 0.23623634 | K23: =IFERROR(historicalFS!K33/SUM(historicalFS!K47:K48),0) -> 0.28342427 | ... M23: =IFERROR(historicalFS!M33/SUM(historicalFS!M47:M48),0) -> 0.14943314 | O23: =IFERROR(AVERAGE(D23:M23),0) -> 0.22566476 | P23: =IFERROR(MEDIAN(D23:M23),0) -> 0.23829802
B24: Self Sustained Growth Rate | D24: =IFERROR(D21*D23,0) -> 0.081271934 | E24: =IFERROR(E21*E23,0) -> 0.070774846 | F24: =IFERROR(F21*F23,0) -> 0.079493423 | G24: =IFERROR(G21*G23,0) -> 0.071591957 | H24: =IFERROR(H21*H23,0) -> 0.071466203 | I24: =IFERROR(I21*I23,0) -> 0.050162679 | J24: =IFERROR(J21*J23,0) -> 0.065019467 | K24: =IFERROR(K21*K23,0) -> 0.092138348 | ... M24: =IFERROR(M21*M23,0) -> 0.027220941 | O24: =IFERROR(AVERAGE(D24:M24),0) -> 0.064092632 | P24: =IFERROR(MEDIAN(D24:M24),0) -> 0.071120525
B25: Interestr Coverage Ratio | D25: =IFERROR((historicalFS!D18-historicalFS!D24)/historicalFS!D21,0) -> 132.16667 | E25: =IFERROR((historicalFS!E18-historicalFS!E24)/historicalFS!E21,0) -> 148.36782 | F25: =IFERROR((historicalFS!F18-historicalFS!F24)/historicalFS!F21,0) -> 226.29851 | G25: =IFERROR((historicalFS!G18-historicalFS!G24)/historicalFS!G21,0) -> 270.21053 | H25: =IFERROR((historicalFS!H18-historicalFS!H24)/historicalFS!H21,0) -> 232.73239 | I25: =IFERROR((historicalFS!I18-historicalFS!I24)/historicalFS!I21,0) -> 216.64179 | J25: =IFERROR((historicalFS!J18-historicalFS!J24)/historicalFS!J21,0) -> 198.6129 | K25: =IFERROR((historicalFS!K18-historicalFS!K24)/historicalFS!K21,0) -> 368.87692 | ... M25: =IFERROR((historicalFS!M18-historicalFS!M24)/historicalFS!M21,0) -> 302.53846 | O25: =IFERROR(AVERAGE(D25:M25),0) -> 240.16158 | P25: =IFERROR(MEDIAN(D25:M25),0) -> 229.51545
B27: Debtor turnover Ratio | D27: =IFERROR(historicalFS!G6/historicalFS!G59,0) -> 12.810174 | E27: =IFERROR(historicalFS!H6/historicalFS!H59,0) -> 17.133858 | F27: =IFERROR(historicalFS!I6/historicalFS!I59,0) -> 11.408748 | G27: =IFERROR(historicalFS!J6/historicalFS!J59,0) -> 13.273907 | H27: =IFERROR(historicalFS!K6/historicalFS!K59,0) -> 17.593027 | I27: =IFERROR(historicalFS!L6/historicalFS!L59,0) -> 19.492905 | J27: =IFERROR(historicalFS!M6/historicalFS!M59,0) -> 6.7279119 | K27: =IFERROR(historicalFS!N6/historicalFS!N59,0) -> 0 | ... M27: =IFERROR(historicalFS!P6/historicalFS!P59,0) -> 0 | O27: =IFERROR(AVERAGE(D27:M27),0) -> 9.8440531 | P27: =IFERROR(MEDIAN(D27:M27),0) -> 12.109461
B28: Creditor turnover Ratio | D28: =IFERROR(historicalFS!G6/historicalFS!G50,0) -> 5.7749151 | E28: =IFERROR(historicalFS!H6/historicalFS!H50,0) -> 5.7325047 | F28: =IFERROR(historicalFS!I6/historicalFS!I50,0) -> 5.023756 | G28: =IFERROR(historicalFS!J6/historicalFS!J50,0) -> 5.973498 | H28: =IFERROR(historicalFS!K6/historicalFS!K50,0) -> 6.3547318 | I28: =IFERROR(historicalFS!L6/historicalFS!L50,0) -> 5.3712936 | J28: =IFERROR(historicalFS!M6/historicalFS!M50,0) -> 4.0950245 | K28: =IFERROR(historicalFS!N6/historicalFS!N50,0) -> 0 | ... M28: =IFERROR(historicalFS!P6/historicalFS!P50,0) -> 0 | O28: =IFERROR(AVERAGE(D28:M28),0) -> 3.8325724 | P28: =IFERROR(MEDIAN(D28:M28),0) -> 5.1975248
B29: Inventory turnover | D29: =IFERROR(historicalFS!G6/historicalFS!G60,0) -> 7.1206144 | E29: =IFERROR(historicalFS!H6/historicalFS!H60,0) -> 3.9547043 | F29: =IFERROR(historicalFS!I6/historicalFS!I60,0) -> 5.747322 | G29: =IFERROR(historicalFS!J6/historicalFS!J60,0) -> 6.4374234 | H29: =IFERROR(historicalFS!K6/historicalFS!K60,0) -> 7.3104763 | I29: =IFERROR(historicalFS!L6/historicalFS!L60,0) -> 6.7874691 | J29: =IFERROR(historicalFS!M6/historicalFS!M60,0) -> 6.1601644 | K29: =IFERROR(historicalFS!N6/historicalFS!N60,0) -> 0 | ... M29: =IFERROR(historicalFS!P6/historicalFS!P60,0) -> 0 | O29: =IFERROR(AVERAGE(D29:M29),0) -> 4.3518174 | P29: =IFERROR(MEDIAN(D29:M29),0) -> 5.9537432
B30: Fixed assset turnover | D30: =IFERROR(historicalFS!G6/historicalFS!G53,0) -> 8.6290851 | E30: =IFERROR(historicalFS!H6/historicalFS!H53,0) -> 8.6941912 | F30: =IFERROR(historicalFS!I6/historicalFS!I53,0) -> 10.285245 | G30: =IFERROR(historicalFS!J6/historicalFS!J53,0) -> 13.342834 | H30: =IFERROR(historicalFS!K6/historicalFS!K53,0) -> 13.663962 | I30: =IFERROR(historicalFS!L6/historicalFS!L53,0) -> 10.122505 | J30: =IFERROR(historicalFS!M6/historicalFS!M53,0) -> 7.4310442 | K30: =IFERROR(historicalFS!N6/historicalFS!N53,0) -> 0 | ... M30: =IFERROR(historicalFS!P6/historicalFS!P53,0) -> 0 | O30: =IFERROR(AVERAGE(D30:M30),0) -> 7.2168867 | P30: =IFERROR(MEDIAN(D30:M30),0) -> 8.6616382
B31: capital turnover | D31: =IFERROR(historicalFS!G6/SUM(historicalFS!G47:G48),0) -> 1.5777993 | E31: =IFERROR(historicalFS!H6/SUM(historicalFS!H47:H48),0) -> 1.4898615 | F31: =IFERROR(historicalFS!I6/SUM(historicalFS!I47:I48),0) -> 1.5506598 | G31: =IFERROR(historicalFS!J6/SUM(historicalFS!J47:J48),0) -> 1.7261151 | H31: =IFERROR(historicalFS!K6/SUM(historicalFS!K47:K48),0) -> 1.691628 | I31: =IFERROR(historicalFS!L6/SUM(historicalFS!L47:L48),0) -> 1.2179015 | J31: =IFERROR(historicalFS!M6/SUM(historicalFS!M47:M48),0) -> 0.91974801 | K31: =IFERROR(historicalFS!N6/SUM(historicalFS!N47:N48),0) -> 0 | ... M31: =IFERROR(historicalFS!P6/SUM(historicalFS!P47:P48),0) -> 0 | O31: =IFERROR(AVERAGE(D31:M31),0) -> 1.0173713 | P31: =IFERROR(MEDIAN(D31:M31),0) -> 1.3538815
B32: Cash conversion Turnover | D32: =IFERROR(historicalFS!G6/historicalFS!G61,0) -> 13.383858 | E32: =IFERROR(historicalFS!H6/historicalFS!H61,0) -> 23.918828 | F32: =IFERROR(historicalFS!I6/historicalFS!I61,0) -> 6.9060018 | G32: =IFERROR(historicalFS!J6/historicalFS!J61,0) -> 4.169365 | H32: =IFERROR(historicalFS!K6/historicalFS!K61,0) -> 2.6603411 | I32: =IFERROR(historicalFS!L6/historicalFS!L61,0) -> 1.8289016 | J32: =IFERROR(historicalFS!M6/historicalFS!M61,0) -> 1.4649366 | K32: =IFERROR(historicalFS!N6/historicalFS!N61,0) -> 0 | ... M32: =IFERROR(historicalFS!P6/historicalFS!P61,0) -> 0 | O32: =IFERROR(AVERAGE(D32:M32),0) -> 5.4332232 | P32: =IFERROR(MEDIAN(D32:M32),0) -> 2.2446214
B34: (in days)
B35: debtor days | D35: =IFERROR(365/D27,0) -> 28.492977 | E35: =IFERROR(365/E27,0) -> 21.302849 | F35: =IFERROR(365/F27,0) -> 31.992992 | G35: =IFERROR(365/G27,0) -> 27.497557 | H35: =IFERROR(365/H27,0) -> 20.746857 | I35: =IFERROR(365/I27,0) -> 18.724762 | J35: =IFERROR(365/J27,0) -> 54.251602 | K35: =IFERROR(365/K27,0) -> 0 | ... M35: =IFERROR(365/M27,0) -> 0 | O35: =IFERROR(AVERAGE(D35:M35),0) -> 20.30096 | P35: =IFERROR(MEDIAN(D35:M35),0) -> 21.024853
B36: payable days | D36: =IFERROR(365/D28,0) -> 63.204393 | E36: =IFERROR(365/E28,0) -> 63.671993 | F36: =IFERROR(365/F28,0) -> 72.654802 | G36: =IFERROR(365/G28,0) -> 61.103227 | H36: =IFERROR(365/H28,0) -> 57.437515 | I36: =IFERROR(365/I28,0) -> 67.953835 | J36: =IFERROR(365/J28,0) -> 89.132556 | K36: =IFERROR(365/K28,0) -> 0 | ... M36: =IFERROR(365/M28,0) -> 0 | O36: =IFERROR(AVERAGE(D36:M36),0) -> 47.515832 | P36: =IFERROR(MEDIAN(D36:M36),0) -> 62.15381
B37: inventory days | D37: =IFERROR(365/D29,0) -> 51.259622 | E37: =IFERROR(365/E29,0) -> 92.295143 | F37: =IFERROR(365/F29,0) -> 63.507839 | G37: =IFERROR(365/G29,0) -> 56.699703 | H37: =IFERROR(365/H29,0) -> 49.928347 | I37: =IFERROR(365/I29,0) -> 53.775567 | J37: =IFERROR(365/J29,0) -> 59.251665 | K37: =IFERROR(365/K29,0) -> 0 | ... M37: =IFERROR(365/M29,0) -> 0 | O37: =IFERROR(AVERAGE(D37:M37),0) -> 42.671789 | P37: =IFERROR(MEDIAN(D37:M37),0) -> 52.517594
B38: cash conversion days | D38: =IFERROR(365/D32,0) -> 27.271658 | E38: =IFERROR(365/E32,0) -> 15.259945 | F38: =IFERROR(365/F32,0) -> 52.852578 | G38: =IFERROR(365/G32,0) -> 87.543307 | H38: =IFERROR(365/H32,0) -> 137.20045 | I38: =IFERROR(365/I32,0) -> 199.57334 | J38: =IFERROR(365/J32,0) -> 249.15755 | K38: =IFERROR(365/K32,0) -> 0 | ... M38: =IFERROR(365/M32,0) -> 0 | O38: =IFERROR(AVERAGE(D38:M38),0) -> 76.885882 | P38: =IFERROR(MEDIAN(D38:M38),0) -> 40.062118
B40: CFO/Sales | D40: =IFERROR(historicalFS!G105/historicalFS!G6,0) -> 0.025236554 | E40: =IFERROR(historicalFS!H105/historicalFS!H6,0) -> -0.020762632 | F40: =IFERROR(historicalFS!I105/historicalFS!I6,0) -> 0.16136281 | G40: =IFERROR(historicalFS!J105/historicalFS!J6,0) -> 0.03191241 | H40: =IFERROR(historicalFS!K105/historicalFS!K6,0) -> 0.12623868 | I40: =IFERROR(historicalFS!L105/historicalFS!L6,0) -> 0.1068074 | J40: =IFERROR(historicalFS!M105/historicalFS!M6,0) -> 0.027813102 | K40: =IFERROR(historicalFS!N105/historicalFS!N6,0) -> 0 | ... M40: =IFERROR(historicalFS!P105/historicalFS!P6,0) -> 0 | O40: =IFERROR(AVERAGE(D40:M40),0) -> 0.045860833 | P40: =IFERROR(MEDIAN(D40:M40),0) -> 0.026524828
B41: CFO/Total asset | D41: =IFERROR(historicalFS!G105/historicalFS!G64,0) -> 0.031273732 | E41: =IFERROR(historicalFS!H105/historicalFS!H64,0) -> -0.024511713 | F41: =IFERROR(historicalFS!I105/historicalFS!I64,0) -> 0.1908547 | G41: =IFERROR(historicalFS!J105/historicalFS!J64,0) -> 0.042674747 | H41: =IFERROR(historicalFS!K105/historicalFS!K64,0) -> 0.16850707 | I41: =IFERROR(historicalFS!L105/historicalFS!L64,0) -> 0.10598764 | J41: =IFERROR(historicalFS!M105/historicalFS!M64,0) -> 0.020887309 | K41: =IFERROR(historicalFS!N105/historicalFS!N64,0) -> 0 | ... M41: =IFERROR(historicalFS!P105/historicalFS!P64,0) -> 0 | O41: =IFERROR(AVERAGE(D41:M41),0) -> 0.053567348 | P41: =IFERROR(MEDIAN(D41:M41),0) -> 0.026080521
B42: CFO/Total debt | D42: =IFERROR(historicalFS!G105/historicalFS!G49,0) -> 0 | E42: =IFERROR(historicalFS!H105/historicalFS!H49,0) -> -14.806723 | F42: =IFERROR(historicalFS!I105/historicalFS!I49,0) -> 105.21528 | G42: =IFERROR(historicalFS!J105/historicalFS!J49,0) -> 30 | H42: =IFERROR(historicalFS!K105/historicalFS!K49,0) -> 194.23457 | I42: =IFERROR(historicalFS!L105/historicalFS!L49,0) -> 224.76596 | J42: =IFERROR(historicalFS!M105/historicalFS!M49,0) -> 220.9 | K42: =IFERROR(historicalFS!N105/historicalFS!N49,0) -> 0 | ... M42: =IFERROR(historicalFS!P105/historicalFS!P49,0) -> 0 | O42: =IFERROR(AVERAGE(D42:M42),0) -> 76.030908 | P42: =IFERROR(MEDIAN(D42:M42),0) -> 15

Sheet forecasting
B3: ='Data Sheet'!B1&" - "&'Data Sheet'!A17 -> HONDA INDIA POWER PRODUCTS LTD - Sales | G3: ='Data Sheet'!B1&" - "&historicalFS!B18 -> HONDA INDIA POWER PRODUCTS LTD - EBITDA
B4: year weigth | C4: year | D4: sales | E4: sales growth | G4: year weigth | H4: year | I4: EBITDA | J4: EBITDA growth
B5: 1 | C5: 2016 | D5: {=TRANSPOSE('Data Sheet'!B17:K17)} -> 672.81 | G5: 1 | H5: 2016 | I5: {=TRANSPOSE(historicalFS!D18:M18)} -> 142.77
B6: =B5+1 -> 2 | C6: =C5+1 -> 2017 | D6: 701.78 | E6: =IFERROR(1-D5/D6,0) -> 0.041280743 | G6: =G5+1 -> 2 | H6: =H5+1 -> 2017 | I6: 152.53 | J6: =IFERROR(1-I5/I6,0) -> 0.063987412
B7: =B6+1 -> 3 | C7: =C6+1 -> 2018 | D7: 767.8 | E7: =IFERROR(1-D6/D7,0) -> 0.085985934 | G7: =G6+1 -> 3 | H7: =H6+1 -> 2018 | I7: 174.13 | J7: =IFERROR(1-I6/I7,0) -> 0.12404525
B8: =B7+1 -> 4 | C8: =C7+1 -> 2019 | D8: 815.88 | E8: =IFERROR(1-D7/D8,0) -> 0.058930235 | G8: =G7+1 -> 4 | H8: =H7+1 -> 2019 | I8: 175.15 | J8: =IFERROR(1-I7/I8,0) -> 0.0058235798
B9: =B8+1 -> 5 | C9: =C8+1 -> 2020 | D9: 848.64 | E9: =IFERROR(1-D8/D9,0) -> 0.038602941 | G9: =G8+1 -> 5 | H9: =H8+1 -> 2020 | I9: 187.32 | J9: =IFERROR(1-I8/I9,0) -> 0.064969037
B10: =B9+1 -> 6 | C10: =C9+1 -> 2021 | D10: 938.94 | E10: =IFERROR(1-D9/D10,0) -> 0.096172279 | G10: =G9+1 -> 6 | H10: =H9+1 -> 2021 | I10: 165.41 | J10: =IFERROR(1-I9/I10,0) -> -0.13245874
B11: =B10+1 -> 7 | C11: =C10+1 -> 2022 | D11: 1156.29 | E11: =IFERROR(1-D10/D11,0) -> 0.18797188 | G11: =G10+1 -> 7 | H11: =H10+1 -> 2022 | I11: 203.23 | J11: =IFERROR(1-I10/I11,0) -> 0.18609457
B12: =B11+1 -> 8 | C12: =C11+1 -> 2023 | D12: 1246.29 | E12: =IFERROR(1-D11/D12,0) -> 0.072214332 | G12: =G11+1 -> 8 | H12: =H11+1 -> 2023 | I12: 260.55 | J12: =IFERROR(1-I11/I12,0) -> 0.21999616
B13: =B12+1 -> 9 | C13: =C12+1 -> 2024 | D13: 989.07 | E13: =IFERROR(1-D12/D13,0) -> -0.26006248 | G13: =G12+1 -> 9 | H13: =H12+1 -> 2024 | I13: 181.96 | J13: =IFERROR(1-I12/I13,0) -> -0.43190811
B14: =B13+1 -> 10 | C14: =C13+1 -> 2025 | D14: 794.23 | E14: =IFERROR(1-D13/D14,0) -> -0.24531937 | G14: =G13+1 -> 10 | H14: =H13+1 -> 2025 | I14: 179.12 | J14: =IFERROR(1-I13/I14,0) -> -0.015855293
B15: =B14+1 -> 11 | C15: =C14+1 -> 2026 | D15: =FORECAST(B15,_xlfn.ANCHORARRAY($D$5),$B$5:$B$14) -> 1113.4327 | E15: =IFERROR(1-D14/D15,0) -> 0.2866834 | G15: =G14+1 -> 11 | H15: =H14+1 -> 2026 | I15: =FORECAST(G15,_xlfn.ANCHORARRAY($I$5),$G$5:$G$14) -> 216.47 | J15: =IFERROR(1-I14/I15,0) -> 0.17254123
B16: =B15+1 -> 12 | C16: =C15+1 -> 2027 | D16: =FORECAST(B16,_xlfn.ANCHORARRAY($D$5),$B$5:$B$14) -> 1153.4799 | E16: =IFERROR(1-D15/D16,0) -> 0.034718605 | G16: =G15+1 -> 12 | H16: =H15+1 -> 2027 | I16: =FORECAST(G16,_xlfn.ANCHORARRAY($I$5),$G$5:$G$14) -> 222.69782 | J16: =IFERROR(1-I15/I16,0) -> 0.027965331
B17: =B16+1 -> 13 | C17: =C16+1 -> 2028 | D17: =FORECAST(B17,_xlfn.ANCHORARRAY($D$5),$B$5:$B$14) -> 1193.5271 | E17: =IFERROR(1-D16/D17,0) -> 0.033553668 | G17: =G16+1 -> 13 | H17: =H16+1 -> 2028 | I17: =FORECAST(G17,_xlfn.ANCHORARRAY($I$5),$G$5:$G$14) -> 228.92564 | J17: =IFERROR(1-I16/I17,0) -> 0.027204547
B18: =B17+1 -> 14 | C18: =C17+1 -> 2029 | D18: =FORECAST(B18,_xlfn.ANCHORARRAY($D$5),$B$5:$B$14) -> 1233.5743 | E18: =IFERROR(1-D17/D18,0) -> 0.03246437 | G18: =G17+1 -> 14 | H18: =H17+1 -> 2029 | I18: =FORECAST(G18,_xlfn.ANCHORARRAY($I$5),$G$5:$G$14) -> 235.15345 | J18: =IFERROR(1-I17/I18,0) -> 0.02648406
B19: =B18+1 -> 15 | C19: =C18+1 -> 2030 | D19: =FORECAST(B19,_xlfn.ANCHORARRAY($D$5),$B$5:$B$14) -> 1273.6215 | E19: =IFERROR(1-D18/D19,0) -> 0.031443574 | G19: =G18+1 -> 15 | H19: =H18+1 -> 2030 | I19: =FORECAST(G19,_xlfn.ANCHORARRAY($I$5),$G$5:$G$14) -> 241.38127 | J19: =IFERROR(1-I18/I19,0) -> 0.025800751

Sheet Sheet1
A1: Open | B1: High | C1: Low | D1: Close | E1: Adj Close | F1: Volume | G1: Dividends | H1: Stock Splits
A2: 2663.8501 | B2: 2669.3999 | C2: 2588.05 | D2: 2620.05 | E2: 2518.4358 | F2: 5372834 | G2: 0 | H2: 0
A3: 2624.95 | B3: 2626 | C3: 2511.8501 | D3: 2544 | E3: 2445.3352 | F3: 8467752 | G3: 0 | H3: 0
A4: 2546 | B4: 2584.6001 | C4: 2531 | D4: 2565.3999 | E4: 2465.9053 | F4: 8634421 | G4: 0 | H4: 0
A5: 2565.3999 | B5: 2565.3999 | C5: 2365.45 | D5: 2428.3 | E5: 2334.1226 | F5: 8285566 | G5: 0 | H5: 0
A6: 2410 | B6: 2511.55 | C6: 2410 | D6: 2452.6001 | E6: 2357.4802 | F6: 8509455 | G6: 0 | H6: 0
A7: 2464 | B7: 2464.75 | C7: 2399 | D7: 2424.1499 | E7: 2330.1331 | F7: 6667167 | G7: 0 | H7: 0
A8: 2424.1001 | B8: 2429.8501 | C8: 2346.75 | D8: 2375.25 | E8: 2283.1299 | F8: 8565297 | G8: 0 | H8: 0
A9: 2389.5 | B9: 2422.8 | C9: 2365.75 | D9: 2394.1001 | E9: 2301.249 | F9: 6206747 | G9: 0 | H9: 0
A10: 2391.1001 | B10: 2438.8 | C10: 2380 | D10: 2409.7 | E10: 2316.2439 | F10: 7755500 | G10: 0 | H10: 0
A11: 2416.2 | B11: 2427.8999 | C11: 2375.3 | D11: 2419.55 | E11: 2325.7119 | F11: 6263275 | G11: 0 | H11: 0
A12: 2409 | B12: 2413 | C12: 2301.8501 | D12: 2327.7 | E12: 2237.4241 | F12: 10419505 | G12: 0 | H12: 0
A13: 2320.8 | B13: 2325 | C13: 2232.05 | D13: 2256.55 | E13: 2169.0334 | F13: 16715348 | G13: 0 | H13: 0
... A106: 2288.8999 | B106: 2326 | C106: 2280 | D106: 2323 | E106: 2323 | F106: 4726381 | G106: 0 | H106: 0

Sheet Data>
A1: DA

Sheet Data Sheet
A1: COMPANY NAME | B1: HONDA INDIA POWER PRODUCTS LTD | E1: =IF(B2<>B3, "A NEW VERSION OF THE WORKSHEET IS AVAILABLE", "")
A2: LATEST VERSION | B2: 2.1 | E2: PLEASE DO NOT MAKE ANY CHANGES TO THIS SHEET
A3: CURRENT VERSION | B3: 2.1
A5: META
A6: Number of shares | B6: =IF(B9>0, B9/B8, 0) -> 1.0140091
A7: Face Value | B7: 10
A8: Current Price | B8: 2349.9
A9: Market Capitalization | B9: 2382.82
A15: PROFIT & LOSS
A16: Report Date | B16: 42460 | C16: 42825 | D16: 43190 | E16: 43555 | F16: 43921 | G16: 44286 | H16: 44651 | I16: 45016 | J16: 45382 | K16: 45747
A17: Sales | B17: 672.81 | C17: 701.78 | D17: 767.8 | E17: 815.88 | F17: 848.64 | G17: 938.94 | H17: 1156.29 | I17: 1246.29 | J17: 989.07 | K17: 794.23
A18: Raw Material Cost | B18: 377.43 | C18: 431.96 | D18: 430.28 | E18: 512.89 | F18: 593.93 | G18: 552.97 | H18: 746.37 | I18: 750.74 | J18: 598.03 | K18: 422.58
A19: Change in Inventory | B19: -21.2 | C19: 15.93 | D19: -25.54 | E19: 12.08 | F19: 91.62 | G19: -55.04 | H19: 14.4 | I19: 0.29 | J19: -2.74 | K19: -21.41
A20: Power and Fuel | B20: 6.26 | C20: 5.24 | D20: 5.94 | E20: 7.31 | F20: 8.19 | G20: 6.8 | H20: 9.41 | I20: 11.81 | J20: 8.75 | K20: 7.87
A21: Other Mfr. Exp | B21: 4.54 | C21: 10.23 | D21: 10.01 | E21: 11.2 | F21: 13.88 | G21: 11.5 | H21: 12.59 | I21: 16.59 | J21: 13.84 | K21: 12.19
A22: Employee Cost | B22: 65.62 | C22: 72.44 | D22: 86.49 | E22: 98.46 | F22: 114.36 | G22: 107.4 | H22: 117.4 | I22: 127.06 | J22: 128.28 | K22: 133.66
A23: Selling and admin | B23: 94.14 | C23: 92.18 | D23: 96.69 | E23: 99.47 | F23: 107.68 | G23: 120.99 | H23: 172.6 | I23: 190.42 | J23: 127.25 | K23: 94.29
A24: Other Expenses | B24: 15.15 | C24: 9.4 | D24: 10.27 | E24: 7.78 | F24: 9.13 | G24: 11.7 | H24: 9.65 | I24: 14.8 | J24: 11.1 | K24: 14.49
A25: Other Income | B25: 11.32 | C25: 16.17 | D25: 14.94 | E25: 14.16 | F25: 20.13 | G25: 14.53 | H25: 16.84 | I25: 1.67 | J25: 45.4 | K25: 42.28
A26: Depreciation | B26: 23.82 | C26: 23.45 | D26: 22.51 | E26: 21.13 | F26: 22.08 | G26: 20.26 | H26: 18.52 | I26: 20.78 | J26: 20.22 | K26: 21.8
A27: Interest | B27: 0.9 | C27: 0.87 | D27: 0.67 | E27: 0.57 | F27: 0.71 | G27: 0.67 | H27: 0.93 | I27: 0.65 | J27: 0.53 | K27: 0.52
... A31: Dividend Amount | B31: 6.08 | C31: 7.6 | D31: 9.13 | E31: 10.14 | F31: 12.68 | G31: 10.14 | H31: 15.21 | I31: 16.73 | J31: 17.74 | K31: 21.8
A40: Quarters
A41: Report Date | B41: 45107 | C41: 45199 | D41: 45291 | E41: 45382 | F41: 45473 | G41: 45565 | H41: 45657 | I41: 45747 | J41: 45838 | K41: 45930
A42: Sales | B42: 209.96 | C42: 284.57 | D42: 263.38 | E42: 231.16 | F42: 144.17 | G42: 177.2 | H42: 204.18 | I42: 268.68 | J42: 154.91 | K42: 175.61
A43: Expenses | B43: 189.65 | C43: 249.34 | D43: 230.38 | E43: 220.71 | F43: 127.69 | G43: 170.2 | H43: 183.38 | I43: 225.28 | J43: 146.47 | K43: 164.28
A44: Other Income | B44: 7.57 | C44: 11.93 | D44: 10.01 | E44: 15.89 | F44: 10.73 | G44: 9.89 | H44: 10.4 | I44: 11.26 | J44: 9.92 | K44: 9.48
A45: Depreciation | B45: 5.01 | C45: 4.98 | D45: 4.97 | E45: 5.26 | F45: 5.34 | G45: 5.36 | H45: 5.41 | I45: 5.69 | J45: 5.53 | K45: 5.71
A46: Interest | B46: 0.05 | C46: 0.05 | D46: 0.05 | E46: 0.29 | F46: 0.04 | G46: 0.05 | H46: 0.05 | I46: 0.32 | J46: 0.04 | K46: 0.03
A47: Profit before tax | B47: 22.82 | C47: 42.13 | D47: 37.99 | E47: 20.79 | F47: 21.83 | G47: 11.48 | H47: 25.74 | I47: 48.65 | J47: 12.79 | K47: 15.07
A48: Tax | B48: 5.92 | C48: 10.94 | D48: 9.67 | E48: 4.99 | F48: 5.68 | G48: 2.94 | H48: 6.65 | I48: 12.49 | J48: 3.31 | K48: 3.9
A49: Net profit | B49: 16.9 | C49: 31.19 | D49: 28.32 | E49: 15.8 | F49: 16.15 | G49: 8.54 | H49: 19.09 | I49: 36.16 | J49: 9.48 | K49: 11.17
A50: Operating Profit | B50: 20.31 | C50: 35.23 | D50: 33 | E50: 10.45 | F50: 16.48 | G50: 7 | H50: 20.8 | I50: 43.4 | J50: 8.44 | K50: 11.33
A55: BALANCE SHEET
A56: Report Date | B56: 42460 | C56: 42825 | D56: 43190 | E56: 43555 | F56: 43921 | G56: 44286 | H56: 44651 | I56: 45016 | J56: 45382 | K56: 45747
A57: Equity Share Capital | B57: 10.14 | C57: 10.14 | D57: 10.14 | E57: 10.14 | F57: 10.14 | G57: 10.14 | H57: 10.14 | I57: 10.14 | J57: 10.14 | K57: 10.14
A58: Reserves | B58: 356.43 | C58: 412.37 | D58: 464.31 | E58: 506.96 | F58: 559.47 | G58: 595.37 | H58: 659.74 | I58: 726.6 | J58: 801.97 | K58: 853.39
A59: Borrowings | F59: 1.19 | G59: 1.44 | H59: 1.23 | I59: 0.81 | J59: 0.47 | K59: 0.1
A60: Other Liabilities | B60: 113.36 | C60: 113.63 | D60: 124.46 | E60: 141.28 | F60: 148.04 | G60: 186.9 | H60: 193.57 | I60: 196.12 | J60: 184.14 | K60: 193.95
A61: Total | B61: 479.93 | C61: 536.14 | D61: 598.91 | E61: 658.38 | F61: 718.84 | G61: 793.85 | H61: 864.68 | I61: 933.67 | J61: 996.72 | K61: 1057.58
A62: Net Block | B62: 112.46 | C62: 106.73 | D62: 100.73 | E62: 94.55 | F62: 97.61 | G62: 91.29 | H62: 86.66 | I62: 91.21 | J62: 97.71 | K62: 106.88
A63: Capital Work in Progress | B63: 0.49 | C63: 0.33 | D63: 0.94 | E63: 3.44 | F63: 1.89 | G63: 2.47 | H63: 12.69 | I63: 9.24 | J63: 7.38 | K63: 7.83
A64: Investments
A65: Other Assets | B65: 366.98 | C65: 429.08 | D65: 497.24 | E65: 560.39 | F65: 619.34 | G65: 700.09 | H65: 765.33 | I65: 833.22 | J65: 891.63 | K65: 942.87
A66: Total | B66: 479.93 | C66: 536.14 | D66: 598.91 | E66: 658.38 | F66: 718.84 | G66: 793.85 | H66: 864.68 | I66: 933.67 | J66: 996.72 | K66: 1057.58
A67: Receivables | B67: 33.64 | C67: 26.38 | D67: 63.6 | E67: 63.69 | F67: 49.53 | G67: 82.3 | H67: 87.11 | I67: 70.84 | J67: 50.74 | K67: 118.05
A68: Inventory | B68: 92.32 | C68: 123.32 | D68: 93.13 | E68: 114.58 | F68: 214.59 | G68: 163.37 | H68: 179.62 | I68: 170.48 | J68: 145.72 | K68: 128.93
A69: Cash & Bank | B69: 155.45 | C69: 142.14 | D69: 191.83 | E69: 60.96 | F69: 35.48 | G69: 135.96 | H69: 277.33 | I69: 468.47 | J69: 540.8 | K69: 542.16
A70: No. of Equity Shares | B70: 10143071 | C70: 10143071 | D70: 10143071 | E70: 10143071 | F70: 10143071 | G70: 10143071 | H70: 10143071 | I70: 10143071 | J70: 10144000 | K70: 10144000
A71: New Bonus Shares
A72: Face value | B72: 10 | C72: 10 | D72: 10 | E72: 10 | F72: 10 | G72: 10 | H72: 10 | I72: 10 | J72: 10 | K72: 10
A80: CASH FLOW:
A81: Report Date | B81: 42460 | C81: 42825 | D81: 43190 | E81: 43555 | F81: 43921 | G81: 44286 | H81: 44651 | I81: 45016 | J81: 45382 | K81: 45747
A82: Cash from Operating Activity | B82: 101.07 | C82: 39.88 | D82: 55 | E82: 20.59 | F82: -17.62 | G82: 151.51 | H82: 36.9 | I82: 157.33 | J82: 105.64 | K82: 22.09
A83: Cash from Investing Activity | B83: -86.38 | C83: -13.87 | D83: -65.48 | E83: -12.66 | F83: 47.4 | G83: -92.29 | H83: 16.01 | I83: -148.36 | J83: -96.69 | K83: -69.05
A84: Cash from Financing Activity | B84: -7.32 | C84: -7.73 | D84: -9.4 | E84: -11.13 | F84: -13.11 | G84: -13.59 | H84: -11.29 | I84: -16.2 | J84: -17.54 | K84: -28.45
A85: Net Cash Flow | B85: 7.37 | C85: 18.28 | D85: -19.88 | E85: -3.2 | F85: 16.67 | G85: 45.63 | H85: 41.62 | I85: -7.23 | J85: -8.59 | K85: -75.41
A87: check | B87: =B85=SUM(B82:B84) -> TRUE | C87: =C85=SUM(C82:C84) -> TRUE | D87: =D85=SUM(D82:D84) -> TRUE | E87: =E85=SUM(E82:E84) -> TRUE | F87: =F85=SUM(F82:F84) -> TRUE | G87: =G85=SUM(G82:G84) -> TRUE | H87: =H85=SUM(H82:H84) -> TRUE | I87: =I85=SUM(I82:I84) -> TRUE | ... K87: =K85=SUM(K82:K84) -> TRUE
A90: PRICE: | B90: 1314.5 | C90: 1336.4 | D90: 1341.6 | E90: 1089 | F90: 840.4 | G90: 956.45 | H90: 1234 | I90: 2014.2 | J90: 2212.85 | K90: 2025.2
A92: DERIVED:
A93: Adjusted Equity Shares in Cr | B93: 1.01 | C93: 1.01 | D93: 1.01 | E93: 1.01 | F93: 1.01 | G93: 1.01 | H93: 1.01 | I93: 1.01 | J93: 1.01 | K93: 1.01

Sheet Cash Flow Data
C2: 41699 | D2: 42064 | E2: 42430 | F2: 42795 | G2: 43160 | H2: 43525 | I2: 43891 | J2: 44256 | K2: 44621 | L2: 44986 | M2: 45352 | N2: 45717
B3: Cash from Operating Activity - | C3: 16 | D3: 43 | E3: 101 | F3: 40 | G3: 55 | H3: 21 | I3: -18 | J3: 152 | K3: 37 | L3: 157 | M3: 106 | N3: 22
B4: Profit from operations | C4: 51 | D4: 74 | E4: 91 | F4: 97 | G4: 103 | H4: 93 | I4: 95 | J4: 72 | K4: 108 | L4: 137 | M4: 105 | N4: 97
B5: Receivables | C5: -12 | D5: 1 | E5: 4 | F5: 5 | G5: -38 | H5: -1 | I5: 14 | J5: -32 | K5: -6 | L5: 15 | M5: 21 | N5: -68
B6: Inventory | C6: -6 | D6: -11 | E6: 29 | F6: -24 | G6: 30 | H6: -21 | I6: -100 | J6: 51 | K6: -16 | L6: 9 | M6: 25 | N6: 17
B7: Payables | C7: 2 | D7: 15 | E7: -6 | F7: 12 | G7: 5 | H7: 8 | I7: 5 | J7: 27 | K7: 3 | L7: -23 | M7: 5 | N7: -18
B8: Loans Advances | C8: -9 | D8: -15 | E8: -1 | F8: 0 | G8: 0 | H8: 0 | I8: 0 | J8: 0 | K8: 0 | L8: 0 | M8: 0 | N8: 0
B9: Other WC items | C9: 3 | D9: 3 | E9: 9 | F9: -13 | G9: -8 | H9: -19 | I9: -6 | J9: 52 | K9: -25 | L9: 75 | M9: -29 | N9: 26
B10: Working capital changes | C10: -22 | D10: -7 | E10: 34 | F10: -20 | G10: -10 | H10: -34 | I10: -87 | J10: 98 | K10: -44 | L10: 77 | M10: 22 | N10: -43
B11: Direct taxes | C11: -14 | D11: -24 | E11: -25 | F11: -37 | G11: -38 | H11: -35 | I11: -30 | J11: -18 | K11: -27 | L11: -39 | M11: -25 | N11: -32
B12: Other operating items | C12: 0 | D12: 0 | E12: 0 | F12: 0 | G12: 0 | H12: -4 | I12: 4 | J12: 0 | K12: 0 | L12: -18 | M12: 4 | N12: 0
B13: Cash from Investing Activity - | C13: -13 | D13: -44 | E13: -86 | F13: -14 | G13: -65 | H13: -13 | I13: 47 | J13: -92 | K13: 16 | L13: -148 | M13: -97 | N13: -69
B14: Fixed assets purchased | C14: -20 | D14: -27 | E14: -13 | F14: -13 | G14: -16 | H14: -18 | I14: -22 | J14: -15 | K14: -17 | L14: -30 | M14: -23 | N14: -41
... B25: Net Cash Flow | C25: -1 | D25: -5 | E25: 7 | F25: 18 | G25: -20 | H25: -3 | I25: 17 | J25: 46 | K25: 42 | L25: -7 | M25: -9 | N25: -75
